Workbook

Sheet PARTICULAR
F1: =COUNTA(F3:F96) -> 74
A2: Coluna 1 | B2: . | C2: . 2 | D2: C | E2: Coluna 5 | F2: NOME | G2: FICHA | H2: TURMA | I2: IDADE | J2: NASCIMENTO | K2: CPF | L2: DATA INÍCIO: | M2: DIAS | N2: TELEFONE: | O2: JANEIRO | P2: FEVEREIRO | Q2: MARÇO | R2: ABRIL | S2: MAIO | T2: JUNHO | U2: JULHO | V2: AGOSTO | W2: SETEMBRO | X2: OUTUBRO | Y2: NOVEMBRO | Z2: DEZEMBRO | AA2: VENCIMENTO | AB2: ELETRO | AC2: ATESTADO DE APTIDÃO | AD2: COMPROVANTE DE RESIDÊNCIA | AE2: CARTEIRA DE VACINAÇÃO | AF2: CARTÃO SUS | AG2: BOLETIM | AH2: TIPO SANGUÍNEO | AI2: DADOS FISCAIS | AJ2: ESCOLA | AK2: ENDEREÇO: | AL2: CIDADE | AM2: -
E3: =SUMPRODUCT((AB3:AL3<>"")*(AB3:AL3<>"-")) -> 4 | F3: ÁLVARO RIFFEL COUTO | G3: OK | H3: TURMA 3 (TARDE) | I3: =INT((TODAY()-J3)/365.25) -> 8 | J3: 43167 | L3: 46220 | M3: 4 | N3: 47 991841767 47 996786075 47 989134934 | O3: - | P3: - | Q3: - | R3: - | S3: - | T3: - | U3: 46234 | V3: TRANCOU | W3: 46245 | AA3: 10 | AI3: RAIRA DOMINGUES RIFFEL - 030.871.020-75 - RAIRIFF.27@GMAIL.COM | AJ3: ANTONIO LUCIO | AK3: R. ISRAEL 431 | AL3: BC
E4: =SUMPRODUCT((AB4:AL4<>"")*(AB4:AL4<>"-")) -> 5 | F4: ANTHONY GABRIEL DA SILVA | G4: OK | H4: TURMA 7 (TARDE) | I4: =INT((TODAY()-J4)/365.25) -> 11 | J4: 42267 | K4: 130.396.239-07 | L4: 46237 | M4: 3 | N4: 47 9121-1515 | O4: - | P4: - | Q4: - | R4: - | S4: - | T4: - | U4: - | V4: 46235 | W4: 46269 | AA4: 10 | AH4: O+ | AI4: ANTONIEL ANTONIO DA SILVA - 946.553.329-72 - ANTONIELSILVA@GSM.SILVA.COM.BR | AJ4: VISÃO | AK4: R. GUAMAPARIM, 359 | AL4: CAMBORIU
E5: =SUMPRODUCT((AB5:AL5<>"")*(AB5:AL5<>"-")) -> 7 | F5: ANTÔNIO JACOMETTO NETO | G5: OK | H5: TURMA 7 (TARDE) | I5: =INT((TODAY()-J5)/365.25) -> 7 | J5: 43440 | K5: 146.695.329-28 | L5: 46273 | M5: 2 | N5: 47 9731-7920 | O5: - | P5: - | Q5: - | R5: - | S5: - | T5: - | U5: - | V5: - | W5: 46273 | AA5: 10 | AD5: OK | AF5: UNIMED | AH5: A+ | AI5: LUCIANE GONÇALVES - 031.619.119-11 - LUEMUNHOZ@GMAIL.COM | AJ5: COC | AK5: RUA NEPAL, 289 | AL5: BC
E6: =SUMPRODUCT((AB6:AL6<>"")*(AB6:AL6<>"-")) -> 7 | F6: ANTÔNIO SALVADOR SOARES | G6: OK | H6: TURMA 6 (MANHÃ) | I6: =INT((TODAY()-J6)/365.25) -> 7 | J6: 43638 | K6: 151.647.179-21 | L6: - | M6: 2 | N6: MÃE 47 9615-0551 | O6: - | P6: - | Q6: - | R6: - | S6: - | T6: 46209 | U6: 46244 | V6: 46254 | W6: 46286 | AA6: 25 | AB6: 2026 | AC6: OK | AD6: OK | AE6: OK | AF6: OK | AH6: A- | AI6: ALEX MARCELINO SOARES 082.649.079-46 - ALEXMARCELINOSOARES@GMAIL.COM | AJ6: - | AK6: - | AL6: -
B7: X | E7: =SUMPRODUCT((AB7:AL7<>"")*(AB7:AL7<>"-")) -> 6 | F7: ARTHUR HINCKEL DALLAGNO | G7: OK | H7: TURMA 7 (TARDE) | I7: =INT((TODAY()-J7)/365.25) -> 10 | J7: 42375 | K7: 130.236.229.14 | L7: - | M7: 4 | N7: MÃE: 47 9 9224 1881 PAI: 47 9 9621 9678 | O7: - | P7: 46076 | Q7: 46090 | R7: 46119 | S7: 46147 | T7: 46199 | U7: 46268 | V7: 46275 | W7: 46300 | AA7: 20 | AD7: ok | AE7: OK | AI7: MAICON MEZAVILLA DALLAGNO - 005.676.820-64 - MAICONDALLAGNO@GMAIL.COM | AJ7: TANIA REGINA | AK7: R. GUARAPARIM - N 130, TABULEIRO | AL7: CAMBORIÚ
E8: =SUMPRODUCT((AB8:AL8<>"")*(AB8:AL8<>"-")) -> 6 | F8: ARTHUR LEONARDO SIMAS | G8: OK | H8: TURMA 3 (TARDE) | I8: =INT((TODAY()-J8)/365.25) -> 9 | J8: 42785 | K8: 136.366.614-30 | L8: 46259 | M8: 3 | N8: 47999131305 | O8: - | P8: - | Q8: - | R8: - | S8: - | T8: - | U8: - | V8: 46259 | AA8: 28 | AD8: OK | AG8: 2026 | AI8: ANDERSON L SIMAS - 025.031.329-44 - ANDERSONSIMAS@HOTMAIL.COM | AJ8: ARMANDO CESAR | AK8: R. SAO LUIZ, VILA REAL, 670 | AL8: CAMBOTIÚ
E9: =SUMPRODUCT((AB9:AL9<>"")*(AB9:AL9<>"-")) -> 4 | F9: ARTHUR VALENDORFF DE CARVALHO | G9: OK | H9: TURMA 2 (MANHÃ) | I9: =INT((TODAY()-J9)/365.25) -> 11 | J9: 42146 | L9: 46235 | M9: 4 | N9: MÃE: 4799241881 PAI: 47 9962149678 | O9: - | P9: - | Q9: - | R9: - | S9: - | T9: - | U9: - | V9: - | W9: 46273 | AA9: 10 | AI9: DANIELE APARECIDA VALLENDORFF - 025.969.189-51 - DANIELE_VALENDORFF@HOTMAIL.COM | AJ9: VISÃO | AK9: R. CEREJEIRA - N 383, TABULEIRO | AL9: CAMBORIÚ
E10: =SUMPRODUCT((AB10:AL10<>"")*(AB10:AL10<>"-")) -> 0 | F10: AUGUSTO TESTONI | I10: =INT((TODAY()-J10)/365.25) -> 126
B11: X | E11: =SUMPRODUCT((AB11:AL11<>"")*(AB11:AL11<>"-")) -> 4 | F11: AYLA G. MELLO SHFFNAN | G11: OK | H11: TURMA 3 (TARDE) | I11: =INT((TODAY()-J11)/365.25) -> 6 | J11: 43863 | K11: 154.225.199-06 | L11: 46197 | M11: 2 | N11: MÃE 4796404126 | O11: - | P11: - | Q11: - | R11: - | S11: - | T11: 46197 | U11: 46279 | V11: TRANCOU | W11: 46280 | AA11: 10 | AC11: OK | AD11: OK | AE11: OK | AF11: OK
E12: =SUMPRODUCT((AB12:AL12<>"")*(AB12:AL12<>"-")) -> 0 | F12: BENICIO BUSATTO | H12: TURMA 7 (TARDE) | I12: 12 | L12: - | M12: 2 | N12: 47 9646-5895 | O12: - | P12: - | Q12: - | R12: - | S12: - | T12: - | U12: - | V12: - | W12: 46288 | AI12: -
E13: =SUMPRODUCT((AB13:AL13<>"")*(AB13:AL13<>"-")) -> 2 | F13: BERNARDO DE LIMA LINDNER | H13: TURMA 7 (TARDE) | I13: 12 | J13: 42579 | K13: 146.644.509-23 | L13: 46308 | M13: 2 | N13: 47 9901-5429 | O13: - | P13: - | Q13: - | R13: - | S13: - | T13: - | U13: -- | V13: - | W13: - | X13: 46308 | AA13: 15 | AC13: OK | AH13: O+
B14: X | C14: AGOSTO | E14: =SUMPRODUCT((AB14:AL14<>"")*(AB14:AL14<>"-")) -> 10 | F14: BENJAMIN PIORELLI COSTA | G14: OK | H14: TURMA 3 (TARDE) | I14: =INT((TODAY()-J14)/365.25) -> 9 | J14: 42692 | K14: 137.277.199-90 | L14: 46091 | M14: 3 | N14: 47999425750 47999046645 | O14: - | P14: - | Q14: 46091 | R14: 46183 | S14: 46152 | T14: 46183 | U14: 46213 | V14: 46244 | W14: 46276 | X14: 46276 | Y14: 46276 | Z14: 11/09 + JAN E FEV | AA14: 10 | AB14: 2026 | AC14: OK | AD14: OK | AE14: OK | AF14: OK | AG14: 2026 | AH14: O+ | AI14: - | AJ14: iate club | AK14: RUA COQUEIROS N -70 | AL14: CAMBORIÚ
B15: X | E15: =SUMPRODUCT((AB15:AL15<>"")*(AB15:AL15<>"-")) -> 6 | F15: BENTO GHENO GONÇALVES | G15: OK | H15: TURMA 2 (MANHÃ) | I15: =INT((TODAY()-J15)/365.25) -> 7 | J15: 43509 | K15: 07774625917 | L15: 46058 | M15: 2 | N15: MÃE: 47 9 91230016 PAI: 47 9 9958 4865 | O15: - | P15: 46058 | Q15: 46114 | R15: 46163 | S15: 46194 | T15: 46197 | U15: FERIAS | V15: 46218 | W15: 46247 | AA15: 5 | AD15: OK | AH15: A+ | AI15: ADARA LUZIA GHENO GONÇALVES - 077.746.259-17 - ADARAGHENO@GMAIL.COM | AJ15: ANGLO | AK15: R. 620 - 40, BC | AL15: BC
B16: X | C16: DEZEMBRO | E16: =SUMPRODUCT((AB16:AL16<>"")*(AB16:AL16<>"-")) -> 10 | F16: BERNARDO ROCHA | G16: OK | H16: TURMA 3 (TARDE) | I16: =INT((TODAY()-J16)/365.25) -> 10 | J16: 42514 | K16: 127.114.169-84 | L16: 46166 | M16: 4 | N16: MÃE: 47 9 8422 2164 PAI: 47 9 8467 2537 | O16: 46045 | P16: 46045 | Q16: 46045 | R16: 46045 | S16: 46045 | T16: 46045 | U16: 46045 | V16: 46045 | W16: 46045 | X16: 46045 | Y16: 46045 | Z16: 46045 | AA16: 10 | AB16: 2026 | AD16: OK | AE16: OK | AF16: OK | AG16: 2026 | AH16: B+ | AI16: ROMÁRIO ROCHA SANTOS - 050.426.615-22 - BERNAROMA1005@GMAIL.COM | AJ16: ARTUR SICHMANN | AK16: AV. SANTA CATARINA - 205, CENTRO | AL16: CAMBORIÚ
E17: =SUMPRODUCT((AB17:AL17<>"")*(AB17:AL17<>"-")) -> 4 | F17: BERNARDO BUENO DE ALBURQUERQUE | G17: OK | H17: TURMA 3 (TARDE) | I17: =INT((TODAY()-J17)/365.25) -> 10 | J17: 42476 | K17: 140.857.389-09 | L17: 46303 | M17: 2 | N17: 47999579720 | O17: - | P17: - | Q17: - | R17: - | S17: - | T17: - | U17: - | V17: - | W17: - | X17: 46303 | AA17: 8 | AI17: FERNANDA BUENO - 356.083.688-35 | AJ17: VEREADOR SANTA | AK17: RUA 2000, 955 | AL17: BC
E18: =SUMPRODUCT((AB18:AL18<>"")*(AB18:AL18<>"-")) -> 2 | F18: BRAYAN BELICA DALMOLIN | G18: OK | H18: TURMA 2 (MANHÃ) | I18: =INT((TODAY()-J18)/365.25) -> 9 | J18: 42889 | K18: 133.823.159-63 | L18: 46248 | M18: 1 | N18: 47996425857 47984038891 | O18: - | P18: - | Q18: - | R18: - | S18: - | T18: - | U18: - | V18: 46248 | W18: 46283 | AA18: 15 | AF18: UNIMED | AG18: 2026
E19: =SUMPRODUCT((AB19:AL19<>"")*(AB19:AL19<>"-")) -> 0 | F19: BRENO GABRIEL FERREIRA | H19: TURMA 7 (TARDE) | I19: 9 | L19: 46293 | M19: 3 | N19: 47 9701-7269 | O19: - | P19: - | Q19: - | R19: - | S19: - | T19: - | U19: - | V19: - | W19: 46294
B20: X | D20: x | E20: =SUMPRODUCT((AB20:AL20<>"")*(AB20:AL20<>"-")) -> 10 | F20: CARLOS PYETRO MATOS DE SOUZA | G20: OK | H20: TURMA 7 (TARDE) | I20: =INT((TODAY()-J20)/365.25) -> 12 | J20: 41655 | K20: 148.034.649-79 | L20: - | M20: 2 | N20: MÃE: 47 9 9127 9106 PAI: 47 9 8818 4342 | O20: 46049 | P20: 46097 | Q20: 46136 | R20: 46170 | S20: 46199 | T20: 46220 | U20: 46232 | V20: 46262 | AA20: 27 | AB20: 2026 | AC20: OK | AD20: OK | AE20: OK | AF20: OK | AG20: 2026 | AH20: O+ | AI20: - | AJ20: CAIC | AK20: R. CONCÓRDIA - N 300, MUNICIPIOS | AL20: BC
E21: =SUMPRODUCT((AB21:AL21<>"")*(AB21:AL21<>"-")) -> 7 | F21: CICERO DE CASTRO DAPIEVE | G21: OK | H21: TURMA 2 (MANHÃ) | I21: =INT((TODAY()-J21)/365.25) -> 7 | J21: 43585 | K21: 062.635.560-56 | L21: 46273 | M21: 2 | N21: 55 9720-8363 | O21: - | P21: - | Q21: - | R21: - | S21: - | T21: - | U21: - | V21: - | W21: 46273 | X21: 46308 | AA21: 8 | AE21: OK | AF21: OK | AG21: 2026 | AI21: WAGNER FACCIN DAPIEVE - 030.234.520-59 WAGNERFOCCIN1999@GMAIL.COM | AJ21: EMB DOMINGOS FONSECA | AK21: CEREJEIRA, 181 | AL21: CAMBORIU
E22: =SUMPRODUCT((AB22:AL22<>"")*(AB22:AL22<>"-")) -> 5 | F22: DANIEL ELIAS RODRIGUES SILVA DOS SANTOS | G22: OK | H22: TURMA 3 (TARDE) | I22: =INT((TODAY()-J22)/365.25) -> 6 | J22: 44052 | K22: 156.524.499-00 | L22: 46266 | M22: 2 | N22: 45 9823-3271 | O22: - | P22: - | Q22: - | R22: - | S22: - | T22: - | U22: - | V22: 46258 | W22: 46303 | AA22: 25 | AD22: OK | AI22: EDINEIA NEVES RODRIGUES - 905.745.839-04 | AJ22: CEI NEIDE | AK22: R. JARDIM EUROPA, ST REGINA | AL22: CAMBORIU
E23: =SUMPRODUCT((AB23:AL23<>"")*(AB23:AL23<>"-")) -> 0 | F23: DOM TOAZZA RIGOM | M23: 3 | O23: - | P23: - | Q23: - | R23: - | S23: - | T23: - | U23: - | V23: - | W23: - | X23: 46295
B24: X | E24: =SUMPRODUCT((AB24:AL24<>"")*(AB24:AL24<>"-")) -> 11 | F24: DAVI DE SOUZA SEBEN | G24: OK | H24: TURMA 2 (MANHÃ) | I24: =INT((TODAY()-J24)/365.25) -> 9 | J24: 42697 | K24: 130.002.029-60 | L24: - | M24: 3 | N24: MÃE: 47 9 9117 9866 PAI: 47 9 9763 3129 | O24: 46075 | P24: 46075 | Q24: 46146 | R24: 46146 | S24: 46204 | T24: 46204 | U24: 46280 | V24: 46280 | W24: 46296 | X24: 46308 | AA24: 10 | AB24: 2026 | AC24: OK | AD24: OK | AE24: OK | AF24: OK | AG24: 2026 | AH24: A+ | AI24: ANDRESSA ALVES DE SOUZA SEBEN - 015.458.010-45 - andressa0.7@hotmail.com | AJ24: VEREADOR SANTA | AK24: R. 2870 - N 888, CENTRO | AL24: BC
E25: =SUMPRODUCT((AB25:AL25<>"")*(AB25:AL25<>"-")) -> 3 | F25: DAVI FERREIRA FIDENCIO | G25: OK | H25: TURMA 2 (MANHÃ) | I25: =INT((TODAY()-J25)/365.25) -> 12 | J25: 41676 | K25: 117.863.789-14 | L25: - | M25: 2 | N25: MÃE 4796404126 | O25: - | P25: - | Q25: - | R25: - | S25: - | T25: 46197 | U25: 46279 | V25: TRANCOU | W25: 46280 | AA25: 10 | AC25: OK | AD25: OK | AG25: 2026
B26: X | E26: =SUMPRODUCT((AB26:AL26<>"")*(AB26:AL26<>"-")) -> 8 | F26: DAVI FONSECA BEUTING | G26: OK | H26: TURMA 7 (TARDE) | I26: =INT((TODAY()-J26)/365.25) -> 14 | J26: 40848 | K26: 043.448.749-00 | L26: - | M26: 4 | N26: MÃE: 47 9 9101 9149 | O26: 46049 | P26: 46063 | Q26: 46091 | R26: 46128 | S26: 46153 | T26: 46188 | U26: 46213 | V26: 46252 | W26: 46279 | X26: 46302 | AA26: 10 | AD26: OK | AE26: OK | AF26: OK | AH26: A+ | AI26: ERICA DIETRICH FONSECA - 217.430.709-00 - SIMARAFONSECA@GMAIL.COM | AJ26: IVO SILVEIRA | AK26: R. 1500 - 1830 - BC | AL26: BC
E27: =SUMPRODUCT((AB27:AL27<>"")*(AB27:AL27<>"-")) -> 5 | F27: DAVI GOMES SILVEIRA | G27: OK | H27: TURMA 2 (MANHÃ) | I27: =INT((TODAY()-J27)/365.25) -> 6 | J27: 43855 | K27: 154.128.749-59 | L27: 46212 | M27: 2 | N27: 47 9600-0000 | O27: - | P27: - | Q27: - | R27: - | S27: - | T27: - | U27: 46212 | V27: 46266 | W27: TRANCOU | AA27: 10 | AH27: O+ | AI27: ADRIANO LUZ SILVEIRA - 056.262.799-54 | AJ27: ANGLO | AK27: RUA SASSAFAZ, 835 | AL27: CAMBORIÚ
B28: X | E28: =SUMPRODUCT((AB28:AL28<>"")*(AB28:AL28<>"-")) -> 7 | F28: DAVI MARQUES DA SILVA | G28: OK | H28: TURMA 3 (TARDE) | I28: =INT((TODAY()-J28)/365.25) -> 10 | J28: 42406 | K28: 135.689.799-18 | L28: 2025 | M28: 2 | N28: MÃE: 47 9 9996 2393 PAI: 47 9 9670 9314 | O28: - | P28: - | Q28: - | R28: 46163 | S28: 46163 | T28: 46163 | U28: 46163 | V28: 46163 | W28: 46163 | X28: 46163 | Y28: 46163 | Z28: 46163 | AA28: 5 | AD28: OK | AE28: OK | AF28: OK | AI28: MÁRIO FERNANDO - 981.854.629-68 - mariofernado@hotmail.com | AJ28: ROGÉRIO L. KUHNEN | AK28: R. JERUSALÉM - N 1581, SANTA REGINA | AL28: CAMBORIÚ
B29: X | E29: =SUMPRODUCT((AB29:AL29<>"")*(AB29:AL29<>"-")) -> 5 | F29: EDUARDO PEDRO BOM CORDEIRO | G29: OK | H29: TURMA 3 (TARDE) | I29: =INT((TODAY()-J29)/365.25) -> 11 | J29: 42019 | K29: 119.129.139-17 | L29: - | M29: 2 | N29: MÃE: 41 98784 5809 PAI: 41 98793 8676 | O29: 46045 | P29: 46080 | Q29: 46108 | R29: 46206 | S29: 46147 | T29: 46183 | U29: 46234 | V29: 46268 | AA29: 25 | AD29: ok | AI29: ANDRE RAFAEL CORDEIRO - 052.925.585-55 - | AJ29: VEREADOR SANTA | AK29: R. LEANDRO BERTOLDI - 191, CEDRO | AL29: CAMBORIÚ
B30: X | E30: =SUMPRODUCT((AB30:AL30<>"")*(AB30:AL30<>"-")) -> 9 | F30: EMANUEL SIMAS MACHADO | G30: OK | H30: TURMA 2 (MANHÃ) | I30: =INT((TODAY()-J30)/365.25) -> 11 | J30: 42089 | K30: 13507525925 | L30: - | M30: 3 | N30: MÃE: 47 9 9611 4679 PAI: 47 9 9668 6810 | O30: 46048 | P30: 46087 | Q30: 46119 | R30: 46192 | S30: 46232 | T30: 46240 | U30: 46254 | AA30: 25 | AD30: OK | AE30: OK | AF30: OK | AG30: 2026 | AH30: O+ | AI30: DAIANE CRISTNA PORTO SIMAS - 064.140.549-92 - DAIANE_CAMBORIÚ@HOTMAIL.COM | AJ30: ARTUR SICHMANN | AK30: R. PREFEITO JOSÉ CESARIO PEREIRA - N 158, CENTRO | AL30: CAMBORIÚ
E31: =SUMPRODUCT((AB31:AL31<>"")*(AB31:AL31<>"-")) -> 4 | F31: ENZO TERESKOVAC | G31: OK | H31: TURMA 2 (MANHÃ) | I31: =INT((TODAY()-J31)/365.25) -> 9 | J31: 42947 | K31: 298.136.128-78 | L31: - | M31: 2 | N31: 11 960385894 | O31: - | P31: - | Q31: - | R31: - | S31: - | T31: -- | U31: - | V31: - | W31: 46265 | AA31: 30 | AI31: MARCELO RELVAS TERESKOVAC - 298.136.128-78 - MR.TERESKOVAC@GMAIL.COM | AJ31: FOR LIFE SCHOOL | AK31: RUA GUAMIRIM, 316 | AL31: CAMBORIU
E32: =SUMPRODUCT((AB32:AL32<>"")*(AB32:AL32<>"-")) -> 4 | F32: GABRIEL OSÓRIO GUEDES | G32: OK | H32: TURMA 7 (TARDE) | I32: =INT((TODAY()-J32)/365.25) -> 9 | J32: 42723 | K32: 053.322.370-90 | L32: (MAIO)/2026 | M32: 4 | N32: MÃE: 55 9 8453 4336 | O32: - | P32: - | Q32: - | R32: - | S32: 46163 | T32: 46163 | U32: 46163 | V32: 46240 | W32: 46240 | X32: 46240 | AA32: 5 | AI32: VIRGINIA OSÓRIO - 041.441.270-28 - OSÓRIO.VIRGINIA@GMAIL.COM | AJ32: ANGLO | AK32: R. ALCILA GARCIA - N 252, CENTRO | AL32: CAMBORIÚ
B33: sim | E33: =SUMPRODUCT((AB33:AL33<>"")*(AB33:AL33<>"-")) -> 9 | F33: GABRIEL QUEIRÓZ WITHOFT | G33: OK | H33: TURMA 7 (TARDE) | I33: =INT((TODAY()-J33)/365.25) -> 10 | J33: 42571 | K33: 127.764.529-93 | L33: 46114 | M33: 2 | N33: PAI: 47 9 9949 8560 | O33: - | P33: - | Q33: - | R33: 46136 | S33: 46219 | T33: 46204 | U33: 46275 | V33: 46295 | AA33: 20 | AC33: OK | AD33: OK | AE33: OK | AF33: OK | AG33: 2026 | AI33: JACKSON AMARAL WITHOFT - 042.820.399-06 - JACKSON.AMARAL.IMOVEIS@GMAIL.COM | AJ33: ABALOR | AK33: R. PARANÁ N° 273, MONTE ALEGRE | AL33: CAMBORIÚ
B34: X | E34: =SUMPRODUCT((AB34:AL34<>"")*(AB34:AL34<>"-")) -> 7 | F34: GABRIEL TALES MENOTTI | G34: OK | H34: TURMA 7 (TARDE) | I34: =INT((TODAY()-J34)/365.25) -> 14 | J34: 40905 | K34: 481.045.478-95 | L34: - | M34: 2 | N34: TIA: 48 9 8441 6036 TIO: 48 9 8501 5131 | O34: 46037 | P34: 46068 | Q34: 46098 | R34: 46129 | S34: 46150 | T34: 46181 | U34: 46211 | V34: 46275 | W34: gerar boleto | X34: gerar boleto | Y34: gerar boleto | Z34: gerar boleto + jan e fev | AA34: 15 | AD34: OK | AE34: OK | AH34: B+ | AI34: FABIO VOCCARO DE CARVALHO - 045.784.399-33 - FABINHOVCX@GMAIL.COM | AJ34: ANGLO | AK34: R. LEOPOLDO LEITE - N 81, CENTRO | AL34: CAMBORIÚ
E35: =SUMPRODUCT((AB35:AL35<>"")*(AB35:AL35<>"-")) -> 6 | F35: GIORGIO BERNARDI CADORE | G35: OK | H35: TURMA 2 (MANHÃ) | I35: =INT((TODAY()-J35)/365.25) -> 8 | J35: 43123 | K35: 138.989.789-31 | L35: 46255 | M35: 2 | N35: 47984800201 | O35: - | P35: - | Q35: - | R35: - | S35: - | T35: - | U35: - | V35: 46255 | W35: 46255 | X35: 46255 | Y35: 46255 | Z35: 21/08/2026 + JANEIRO | AA35: - | AB35: 2026 | AC35: OK | AD35: OK | AE35: OK | AF35: OK | AG35: 2026
E36: =SUMPRODUCT((AB36:AL36<>"")*(AB36:AL36<>"-")) -> 7 | F36: GUILHERME DERETTI | G36: OK | H36: TURMA 2 (MANHÃ) | I36: =INT((TODAY()-J36)/365.25) -> 9 | J36: 42725 | K36: 130.381.629-65 | L36: - | N36: 47 9916-1292 | O36: - | P36: - | Q36: - | R36: - | S36: - | T36: - | U36: - | V36: 46258 | W36: 46295 | AA36: 20 | AB36: 2026 | AC36: OK | AD36: ok | AE36: ok | AF36: OK | AG36: 2026 | AH36: A+
B37: X | E37: =SUMPRODUCT((AB37:AL37<>"")*(AB37:AL37<>"-")) -> 9 | F37: GUILHERME PEREIRA DOS SANTOS | G37: OK | H37: TURMA 5 (MANHÃ) | I37: =INT((TODAY()-J37)/365.25) -> 13 | J37: 41247 | K37: 137.234.839-50 | L37: - | M37: 4 | N37: MÃE: 47 999574884 PAI: 47 99957883 | O37: 46051 | P37: 46081 | Q37: 46113 | R37: 46113 | S37: 46175 | T37: 46204 | U37: 46231 | V37: 46253 | W37: 46304 | X37: 46304 | AA37: 20 | AC37: OK | AD37: ok | AE37: OK | AG37: 2026 | AH37: O+ | AI37: GIOVANI CARVALHO DOS SANTOS - 040.639.229-36 - GIOVANICARVALHO4558@GMAIL.COM | AJ37: IVO SILVEIRA | AK37: R. MONTE PAMIR - 199, CONDE | AL37: CAMBORIÚ
B38: X | E38: =SUMPRODUCT((AB38:AL38<>"")*(AB38:AL38<>"-")) -> 11 | F38: GUSTAVO KENJI DA SILVEIRA | G38: OK | H38: TURMA 7 (TARDE) | I38: =INT((TODAY()-J38)/365.25) -> 7 | J38: 43508 | K38: 147.792.789-10 | L38: - | M38: 4 | N38: MAE:47992000766 PAI:47991877070 | O38: - | P38: 46055 | Q38: 46090 | R38: 46119 | S38: 46161 | T38: 46184 | U38: 46213 | V38: 46246 | W38: 46276 | AA38: 15 | AB38: 2026 | AC38: OK | AD38: OK | AE38: OK | AF38: UNIMED | AG38: 2026 | AH38: A+ | AI38: OTAVIO ROCHA-045.887.999-16 - OTSOCHA@GMAIL.COM | AJ38: COC | AK38: RUA ANGELIN 39- TABOLEIRO | AL38: CAMBORIÚ
B39: X | E39: =SUMPRODUCT((AB39:AL39<>"")*(AB39:AL39<>"-")) -> 8 | F39: HENRI CARPENEDO DOS SANTOS | G39: OK | H39: TURMA 2 (MANHÃ) | I39: =INT((TODAY()-J39)/365.25) -> 8 | J39: 43109 | K39: 138.485.599-86 | L39: - | M39: 2 | N39: MÃE: 47 9 9966 4883 PAI: 47 9 9900 5951 | O39: - | P39: - | Q39: 46096 | R39: 46184 | S39: 46184 | T39: 46055 | U39: 46218 | V39: 46254 | W39: 46293 | AA39: 10 | AB39: 2026 | AD39: OK | AF39: OK | AG39: 2026 | AI39: MELINA CARPENEDO - 011.665.520-80 - MELCARPENEDO@GMAIL.COM | AJ39: VEREADORES SANTA | AK39: R. GUARAPARIM - N° 130, 508/4, TABULEIRO | AL39: CAMBORIÚ
E40: =SUMPRODUCT((AB40:AL40<>"")*(AB40:AL40<>"-")) -> 7 | F40: HENRIQUE LOTTI | G40: OK | H40: TURMA 2 (MANHÃ) | I40: =INT((TODAY()-J40)/365.25) -> 8 | J40: 43164 | K40: 140.225.779-16 | L40: 46238 | M40: 3 | N40: 47 8487-5727 | O40: - | P40: - | Q40: - | R40: - | S40: - | T40: - | U40: - | V40: 46238 | W40: 46280 | AA40: 5 | AD40: OK | AE40: OK | AG40: 2026 | AI40: KETLIN LENHARDT LOTTI - 079.241.399-74 | AJ40: CECAM | AK40: R. MASSARANDUBA 553, APTO 302 | AL40: CAMBORIÚ
E41: =SUMPRODUCT((AB41:AL41<>"")*(AB41:AL41<>"-")) -> 5 | F41: HIROYUKI MOTA TUKAMOTO | G41: OK | H41: TURMA 7 (TARDE) | I41: =INT((TODAY()-J41)/365.25) -> 10 | J41: 42478 | K41: 135.970.399-36 | L41: - | M41: 4 | N41: MÃE: 47 99632 0442 PAI: 47 99974 9108 | O41: 46062 | P41: 46171 | Q41: 46171 | R41: - | S41: - | T41: 46179 | U41: 46233 | V41: 46241 | W41: 46269 | X41: 46301 | AA41: 5 | AD41: OK | AE41: OK | AI41: ANGÉLICA MOTA DE MOURA - 107.715.959-56 - ANGELICAMOTAMOURA7@GMAIL.COM | AJ41: CAIC | AK41: - | AL41: CAMBORIÚ
B42: X | C42: JULHO | E42: =SUMPRODUCT((AB42:AL42<>"")*(AB42:AL42<>"-")) -> 8 | F42: ISABELLA MARIA PINHEIRO | G42: OK | H42: TURMA 7 (TARDE) | I42: =INT((TODAY()-J42)/365.25) -> 13 | J42: 41446 | K42: 149.641.959-61 | L42: - | M42: 2 | N42: MÃE: 47 9 9958 9185 PAI: 47 9 9916 3794 | O42: 45845 | P42: 45845 | Q42: 45845 | R42: 45845 | S42: Plano de 12 | T42: Plano de 12 | U42: Plano de 12 | V42: Plano de 12 | W42: Plano de 12 | X42: Plano de 12 | Y42: Plano de 12 | Z42: Plano de 12 | AA42: 10 | AD42: ok | AE42: OK | AF42: OK | AH42: A+ | AI42: MÔNICA GREY NUNES PINHEIRO - 056.518.049-51 - MONICAGREY2011@HOTMAIL.COM | AJ42: CECAM | AK42: BR 101 KM 131 - N 45, VÁRZEA RANCHINHO | AL42: CAMBORIÚ
B43: X | C43: JUNHO | E43: =SUMPRODUCT((AB43:AL43<>"")*(AB43:AL43<>"-")) -> 11 | F43: ISACK CABRAL FINOTTI | G43: OK | H43: TURMA 7 (TARDE) | I43: =INT((TODAY()-J43)/365.25) -> 10 | J43: 42471 | K43: 127.060.779-05 | L43: - | M43: 3 | N43: MÃE: 47 9 9227 4539 PA: -- | O43: Plano 12 meses | P43: de 2025 | Q43: ok | R43: ok | S43: até | T43: junho | U43: 46218 | V43: 46248 | W43: 46248 | X43: 46248 | Y43: 46248 | Z43: 14/08/2026 - janeiro já ok | AA43: 10 | AB43: 2026 | AC43: OK | AD43: OK | AE43: OK | AF43: OK | AG43: 2026 | AH43: A- | AI43: FERNANDA . Z CABRAL - 127.060.779-05 - fernandakabral@hotmail.com | AJ43: VEREADOR SANTA | AK43: R. CABUL - N 330, SANTA REGINA | AL43: CAMBORIÚ
B44: X | E44: =SUMPRODUCT((AB44:AL44<>"")*(AB44:AL44<>"-")) -> 8 | F44: JOÃO GERGENSLEY LAGUERRE | G44: OK | H44: TURMA 2 (MANHÃ) | I44: =INT((TODAY()-J44)/365.25) -> 11 | J44: 42254 | K44: 122 447.269-16 | L44: - | M44: 3 | N44: MÃE: 47 99678 6892 PAI: 47 99624 1437 | O44: 46058 | P44: 46091 | Q44: 46113 | R44: 46171 | S44: 46171 | T44: 46212 | U44: 46248 | V44: 46276 | W44: 46304 | AA44: 15 | AD44: --- | AE44: OK | AF44: OK | AH44: O+ | AI44: MARIA ELDIA GALETTE - 701.624.402-43 - | AJ44: CAIC | AK44: R. CANELINHA - N 445, MUNICIPIOS | AL44: BC
E45: =SUMPRODUCT((AB45:AL45<>"")*(AB45:AL45<>"-")) -> 8 | F45: JOÃO PEDRO KAMINSKI DE OLIVEIRA | G45: OK | H45: TURMA 2 (MANHÃ) | I45: =INT((TODAY()-J45)/365.25) -> 9 | J45: 42921 | K45: 054.846.630-08 | L45: 46281 | M45: 2 | N45: 47 8917-3011 | O45: -- | P45: - | Q45: - | R45: - | S45: - | T45: - | U45: - | V45: - | W45: 46283 | AD45: OK | AE45: OK | AF45: UNIMED | AG45: 2026 | AI45: LEONARDO SMANIOTTO DE OLIVEIRA - 004.752.640-88 | AJ45: QUINTAL MAGICO | AK45: R. MASSARANDUBA, 553 | AL45: CAMBORIU
B46: x | E46: =SUMPRODUCT((AB46:AL46<>"")*(AB46:AL46<>"-")) -> 9 | F46: JOHN ADAMS NERVARD | G46: OK | H46: TURMA 2 (MANHÃ) | I46: =INT((TODAY()-J46)/365.25) -> 9 | J46: 42813 | K46: 8313694 | L46: - | M46: 2 | N46: MÃE: 47 98465 5397 PAI: 47 98479 4099 | O46: 46042 | P46: 46063 | Q46: DINHEIRO | R46: DINHEIRO | S46: 46154 | T46: 46188 | U46: 46212 | V46: 46247 | W46: 46280 | X46: 46304 | AA46: 14 | AD46: OK | AE46: OK | AF46: OK | AG46: 2026 | AH46: B+ | AI46: JEAN NERVARD - 700.420.832-06 - JEANNERVARD@GMAIL.COM | AJ46: CAIC | AK46: RESIDENCIAL 61 | AL46: CAMBORIÚ
E47: =SUMPRODUCT((AB47:AL47<>"")*(AB47:AL47<>"-")) -> 2 | F47: JOSÉ JOAQUIN YUNIS | G47: OK | H47: TURMA 2 (MANHÃ) | I47: =INT((TODAY()-J47)/365.25) -> 9 | J47: 42928 | K47: 001.651.499-81 | L47: 46255 | N47: 47 9777-3329 | O47: - | P47: - | Q47: - | R47: - | S47: - | T47: - | U47: - | V47: 46259 | W47: 46280 | AA47: 21 | AB47: 2026 | AC47: OK
E48: =SUMPRODUCT((AB48:AL48<>"")*(AB48:AL48<>"-")) -> 6 | F48: JOSÉ MIGUEL DA SILVA | G48: OK | H48: TURMA 3 (TARDE) | I48: =INT((TODAY()-J48)/365.25) -> 8 | J48: 43029 | K48: 145.846.459-81 | L48: 46286 | M48: 4 | N48: MÃE: 47 98447 3454 PAI: 47 99125 0508 | O48: - | P48: - | Q48: - | R48: - | S48: - | T48: - | U48: - | V48: - | W48: PLANO DE 12 | X48: PLANO DE 12 | Y48: PLANO DE 12 | Z48: PLANO DE 12 + ATÉ AGOSTO 2026. | AA48: 20 | AC48: OK | AD48: OK | AE48: OK | AF48: OK | AG48: 2026 | AH48: AB+
B49: X | E49: =SUMPRODUCT((AB49:AL49<>"")*(AB49:AL49<>"-")) -> 7 | F49: KALEB FELIPE | G49: OK | H49: TURMA 2 (MANHÃ) | I49: =INT((TODAY()-J49)/365.25) -> 8 | J49: 43346 | K49: 144.530.649-26 | L49: 46091 | M49: 1 | N49: 47999949026 47999325157 | O49: - | P49: - | Q49: 46091 | AA49: 10 | AB49: 2026 | AD49: OK | AE49: OK | AF49: OK | AI49: - | AJ49: DOMINGOS FONSECA | AK49: RUA MONTE OBRIGADA N- 693 | AL49: CAMBORIÚ
B50: sim | E50: =SUMPRODUCT((AB50:AL50<>"")*(AB50:AL50<>"-")) -> 5 | F50: LEONARDO DAVI PEREIRA ROGAL | G50: OK | H50: TURMA 2 (MANHÃ) | I50: =INT((TODAY()-J50)/365.25) -> 11 | J50: 42221 | K50: 122.635.939-69 | L50: 46139 | M50: 1 | N50: MÃE: 47 9932-7549 PAI: 47 99605-1700 | O50: - | P50: Fazer boleto | Q50: todo dia | R50: 15 | S50: - | T50: 46195 | U50: 46217 | V50: 46251 | W50: 46294 | AA50: 15 | AH50: A+ | AI50: WAGNER ADILSON ROGAL - 950.500.519-91 - WAGNERROGAL@GMAIL.COM | AJ50: COC | AK50: R RIO GUAÍRA, N 665- RIO PEQUENO | AL50: CAMBORIÚ
E51: =SUMPRODUCT((AB51:AL51<>"")*(AB51:AL51<>"-")) -> 4 | F51: LORENZO DOS SANTOS DE OLIVEIRA | G51: OK | H51: TURMA 7 (TARDE) | I51: =INT((TODAY()-J51)/365.25) -> 12 | J51: 41630 | K51: 145.493.819-65 | L51: 46266 | M51: 2 | N51: 47991380427 47992245118 | O51: - | P51: - | Q51: - | R51: - | S51: - | T51: - | U51: - | V51: - | W51: 46268 | AA51: 5 | AI51: PRISCILA CANDIDO DOS SANTOS DE OLIVEIRA - 044.491.649-03 | AJ51: LICEU | AK51: RUA 3000, 823 | AL51: BC
E52: =SUMPRODUCT((AB52:AL52<>"")*(AB52:AL52<>"-")) -> 0 | F52: LORENZO PERONIO ZAMBELE | H52: TURMA 2 (MANHÃ) | I52: =INT((TODAY()-J52)/365.25) -> 7 | J52: 43429 | L52: - | N52: 47 9192-1126 | O52: - | P52: 46072 | Q52: 46105 | R52: 46142 | S52: 46199 | T52: 46199 | U52: OK VIAGEM | V52: 46254 | W52: 46289 | AA52: 25 | AI52: -
E53: =SUMPRODUCT((AB53:AL53<>"")*(AB53:AL53<>"-")) -> 6 | F53: LUCAS EVANGELISTA DE SOUZA | H53: TURMA 2 (MANHÃ) | I53: =INT((TODAY()-J53)/365.25) -> 11 | J53: 42277 | K53: 123.069.019-02 | L53: 46111 | M53: 1 | N53: 47 9191-6210 | O53: - | P53: - | Q53: - | R53: 46160 | S53: 46160 | T53: 46195 | U53: 46237 | V53: 46237 | W53: 46286 | AA53: 5 | AC53: OK | AD53: OK | AE53: OK | AF53: OK | AG53: 2026 | AH53: O+
E54: =SUMPRODUCT((AB54:AL54<>"")*(AB54:AL54<>"-")) -> 5 | F54: LUCAS FERNANDO DELAGNELLO | G54: OK | H54: TURMA 2 (MANHÃ) | I54: =INT((TODAY()-J54)/365.25) -> 11 | J54: 42184 | K54: 126.190.659-41 | L54: 46212 | M54: 2 | N54: 47999582838 | O54: - | P54: - | Q54: - | R54: - | S54: - | T54: - | U54: 46212 | V54: 46242 | W54: 46267 | X54: 46303 | AA54: 10 | AD54: OK | AI54: EDVAL FERNANDO DELAGNELLO - 007.280.689-31 | AJ54: ANGLO | AK54: R. HEITOR SANTOS, 511 | AL54: CAMBORIU
B55: X | E55: =SUMPRODUCT((AB55:AL55<>"")*(AB55:AL55<>"-")) -> 7 | F55: LUCAS MENEGUSSO PEREIRA DA ROCHA | G55: OK | H55: TURMA 3 (TARDE) | I55: =INT((TODAY()-J55)/365.25) -> 11 | J55: 42287 | K55: 133.711.239-95 | L55: - | M55: 3 | N55: MÃE: 47 9 9669 0398 PAI: 47 9 9655 7089 | O55: 46115 | P55: 46125 | Q55: 46147 | R55: 46195 | S55: 46212 | T55: 46219 | U55: 46219 | V55: 46254 | W55: 46296 | AA55: 20 | AD55: OK | AE55: OK | AF55: particular | AI55: ROCHEL JORDAN PEREIRA DA ROCHA - 076.014.079-00 - ROCHEL_ROK@HOTMAIL.COM | AJ55: COC | AK55: R. MINAS GERAIS - 398, AREIAS | AL55: CAMBORIÚ
B56: sim | E56: =SUMPRODUCT((AB56:AL56<>"")*(AB56:AL56<>"-")) -> 1 | F56: MARTIN PERONIO ZAMBELE | G56: OK | H56: TURMA 2 (MANHÃ) | I56: =INT((TODAY()-J56)/365.25) -> 5 | J56: 44182 | K56: 157.828.179-25 | L56: 46072 | N56: 47 9192-1126 | O56: _ | P56: 46072 | Q56: 46105 | R56: 46142 | S56: 46199 | T56: 46199 | U56: OK VIAGEM | V56: 46254 | W56: 46289 | AA56: 20 | AD56: ok
E57: =SUMPRODUCT((AB57:AL57<>"")*(AB57:AL57<>"-")) -> 4 | F57: MATHEUS FAGUNDES PACHECO | G57: OK | H57: TURMA 2 (MANHÃ) | I57: =INT((TODAY()-J57)/365.25) -> 10 | J57: 42384 | K57: 124.462.089-08 | L57: - | N57: 47988886894 47989039118 | O57: - | P57: - | Q57: - | R57: - | S57: - | T57: - | U57: - | V57: - | AA57: 20 | AE57: OK | AI57: - | AJ57: Joao goulart | AK57: R 960, 45 | AL57: BC
E58: =SUMPRODUCT((AB58:AL58<>"")*(AB58:AL58<>"-")) -> 8 | F58: MAXIMO ARROYO | G58: OK | H58: TURMA 2 (MANHÃ) | I58: =INT((TODAY()-J58)/365.25) -> 8 | J58: 43298 | K58: 052.219.009-04 | L58: 46279 | M58: 4 | N58: 47 988698599 47 988699769 | O58: - | P58: - | Q58: - | R58: - | S58: - | T58: - | U58: - | V58: - | W58: 46280 | AA58: 15 | AD58: OK | AE58: OK | AF58: OK | AH58: AB+ | AI58: DANIELA BENITEZ - 051.326.149-49 - DANIELAARROYOBR@GMAIL.COM | AJ58: CAIC | AK58: R. SILVEIRA 283 | AL58: CAMBORIU
B59: X | E59: =SUMPRODUCT((AB59:AL59<>"")*(AB59:AL59<>"-")) -> 5 | F59: MIGUEL CORREIA DE FREITAS | G59: OK | H59: TURMA 2 (MANHÃ) | I59: =INT((TODAY()-J59)/365.25) -> 11 | J59: 42039 | K59: 136.379.389-60 | L59: 46045 | M59: 3 | N59: MÃE: 47 99997 3731 PAI: 47 996990530 | O59: 46045 | P59: 46101 | Q59: - | R59: - | S59: - | T59: - | U59: 46227 | V59: 46248 | W59: 46283 | AA59: 10 | AD59: OK | AI59: ELINARA CORREIA DE FREITAS - 935.473.829-04 - ELINARA2202@GMAIL.COM | AJ59: ADVENTISTA | AK59: RUA EMANUEL REBELO DOS SANTOS | AL59: BC
B60: X | E60: =SUMPRODUCT((AB60:AL60<>"")*(AB60:AL60<>"-")) -> 11 | F60: MIGUEL PACHECO DO NASCIMENTO | G60: OK | H60: TURMA 7 (TARDE) | I60: =INT((TODAY()-J60)/365.25) -> 12 | J60: 41811 | K60: 150.845.299-75 | L60: 46048 | M60: 3 | N60: MÃE: 47 99909 3737 PAI: 47 99688 9426 | O60: 26/012026 | P60: 46078 | Q60: 46106 | R60: 46138 | S60: 46165 | T60: 46192 | U60: 46227 | V60: 46258 | W60: 46300 | AA60: 5 | AB60: 2026 | AC60: OK | AD60: OK | AE60: OK | AF60: OK | AG60: 2026 | AH60: O+ | AI60: EDUARDA PACHECO COSTA ROSA - 106.465.879-27 - PACHECODUDDA05@GMAIL.COM | AJ60: TOMAZ FRANCISCO GARCIA | AK60: R. CRICIÚMA N° 259 - MUNICÍPIOS | AL60: BC
E61: =SUMPRODUCT((AB61:AL61<>"")*(AB61:AL61<>"-")) -> 5 | F61: MIGUEL STOLFI FARIAS | G61: OK | H61: TURMA 7 (TARDE) | I61: =INT((TODAY()-J61)/365.25) -> 10 | J61: 42575 | L61: 46231 | M61: 4 | N61: 47 9660-1678 | O61: - | P61: - | Q61: - | R61: - | S61: - | T61: - | U61: 46231 | V61: 46279 | W61: 46279 | AA61: 28 | AH61: A+ | AI61: TAUANE STOLF - 097.246.159-01 - TAUANESTOLF.@GMAIL.COM | AJ61: TOMAZ FRANCISCO GARCIA | AK61: RUA BRUSQUE 584 | AL61: BC
E62: =SUMPRODUCT((AB62:AL62<>"")*(AB62:AL62<>"-")) -> 5 | F62: MIGUEL YUTA KANAI | G62: OK | H62: TURMA 2 (MANHÃ) | I62: =INT((TODAY()-J62)/365.25) -> 11 | J62: 42265 | K62: 123.771.099-50 | L62: - | M62: 2 | N62: 47 9601-1903 | O62: - | P62: - | Q62: - | R62: - | S62: - | T62: - | U62: - | V62: - | W62: 46279 | AA62: 15 | AH62: O+ | AI62: FABIO HIDEKI KANAI - 290.081.068-09 - FHKANAI@YAHOO.COM.BR | AJ62: DOMINGOS FONSCA | AK62: RUA COQUEIROS, 63 | AL62: CAMBORIU
E63: =SUMPRODUCT((AB63:AL63<>"")*(AB63:AL63<>"-")) -> 6 | F63: NICOLLAS HIAN ALVES MARTINS | G63: OK | H63: TURMA 2 (MANHÃ) | I63: =INT((TODAY()-J63)/365.25) -> 11 | J63: 42255 | K63: 050.109.170-09 | L63: 46217 | N63: 54991444752 54992182249 | O63: - | P63: - | Q63: - | R63: - | S63: - | T63: - | U63: 46213 | V63: 46247 | W63: 46281 | AA63: 15 | AD63: OK | AF63: OK | AI63: EUNICE STAN ALVES PINHEIRO - 035.493.770-70 - STANALVESE@ORBENK.COM.BR | AJ63: DOMINGOS FONSECA | AK63: R. SWAMIRIM 100, CAMBORIU | AL63: CAMBORIÚ
E64: =SUMPRODUCT((AB64:AL64<>"")*(AB64:AL64<>"-")) -> 4 | F64: PEDRO DAVI LOCH | G64: OK | H64: TURMA 7 (TARDE) | I64: =INT((TODAY()-J64)/365.25) -> 11 | J64: 42046 | K64: 126.499.179-70 | L64: 46217 | M64: 4 | N64: 47997791710 | O64: - | P64: - | Q64: - | R64: - | S64: - | T64: - | U64: 46217 | V64: 46254 | W64: 46295 | AA64: 10 | AI64: LUANA FERREIRA - 090.171.469-07 | AJ64: CECAM | AK64: R. NORUEGA, 15B | AL64: BC
B65: X | E65: =SUMPRODUCT((AB65:AL65<>"")*(AB65:AL65<>"-")) -> 11 | F65: PEDRO HENRIQUE BELICA GASPAR | G65: OK | H65: TURMA 2 (MANHÃ) | I65: =INT((TODAY()-J65)/365.25) -> 11 | J65: 42168 | K65: 12773955943 | L65: - | M65: 2 | N65: MÃE: 47 99737 9235 PAI: 47 99623 8606 | O65: 46032 | P65: 46066 | Q65: 46094 | R65: 46122 | S65: 46188 | T65: 46188 | U65: 46209 | V65: 46248 | W65: 46276 | X65: 46306 | AA65: 10 | AB65: 2026 | AC65: OK | AD65: OK | AE65: OK | AF65: OK | AG65: 2026 | AH65: B+ | AI65: JEISIANE ROSA BELICA GASPAR - 075.377.239-66 - JRB_BELICA@HOTMAIL.COM | AJ65: TANIA REGINA | AK65: R. MONTE RORAIMA - 446, MONTE ALEGRE | AL65: CAMBORIÚ
E66: =SUMPRODUCT((AB66:AL66<>"")*(AB66:AL66<>"-")) -> 8 | F66: PEDRO HENRIQUE LIMA DA SILVA | G66: OK | H66: TURMA 7 (TARDE) | I66: =INT((TODAY()-J66)/365.25) -> 14 | J66: 41037 | K66: 147.337.219-43 | L66: - | M66: 2 | N66: MÃE: 47 8911-1078 | O66: 46028 | P66: se machucou | Q66: esperar | R66: voltou em | S66: junho | T66: 46178 | U66: 46216 | V66: 46251 | W66: 46280 | AA66: 20 | AD66: ok | AE66: OK | AF66: OK | AH66: B+ | AI66: ALEKSANDRA MIRELLY DE MELO LIMA - 036.803.862-90 - Mirellymelolima301296@gmail.com | AJ66: CEM. NOVA ESPERANÇA | AK66: R. ACADEMICA ALICIA JORGE DE SOUZA | AL66: BC
B67: x | E67: =SUMPRODUCT((AB67:AL67<>"")*(AB67:AL67<>"-")) -> 11 | F67: PEDRO KREHNKE DE OLIVEIRA | G67: OK | H67: TURMA 2 (MANHÃ) | I67: =INT((TODAY()-J67)/365.25) -> 8 | J67: 43179 | K67: 140.426.319-59 | L67: - | M67: 4 | N67: MÃE: 47 99276 2166 PAI: 47 99970 2111 | O67: 46042 | P67: 46063 | Q67: 46090 | R67: 46122 | S67: 46152 | T67: 46183 | U67: 46213 | V67: 46246 | W67: 46269 | AA67: 5 | AB67: 2026 | AC67: OK | AD67: OK | AE67: OK | AF67: OK | AG67: 2026 | AH67: B+ | AI67: ALEXSANDER OLIVEIRA - 026.277.167-51 - ALEXSANDER.OLIV75@GMAIL.COM | AJ67: RECRIARTE | AK67: R. OLGA BERNARDES AMORIM - N 193, CENTRO | AL67: CAMBORIÚ
B68: novo | E68: =SUMPRODUCT((AB68:AL68<>"")*(AB68:AL68<>"-")) -> 4 | F68: PIETRO RIFFEL COUTO | G68: OK | H68: TURMA 3 (TARDE) | I68: =INT((TODAY()-J68)/365.25) -> 12 | J68: 41773 | K68: 061.726.530-59 | L68: 46149 | M68: 4 | N68: MÃE: 47 99184-1767 PAI: 47 99648-6075 | O68: - | P68: - | Q68: - | R68: - | S68: 46149 | T68: 46195 | U68: 46234 | V68: TRANCOU | W68: 46245 | AA68: 10 | AI68: RAÍNA DOMINGUES RIFFEL - 030.871.020-75 - RAIRIFF27@GMAIL.COM | AJ68: ENERGIA | AK68: R. ISRAEL, NAÇÕES - BC | AL68: BC
E69: =SUMPRODUCT((AB69:AL69<>"")*(AB69:AL69<>"-")) -> 8 | F69: RAJI GHAITH | G69: OK | H69: TURMA 7 (TARDE) | I69: =INT((TODAY()-J69)/365.25) -> 9 | J69: 42865 | K69: 120.476.641-01 | L69: 46237 | M69: 2 | N69: 47 8880-8849 | O69: - | P69: - | Q69: - | R69: - | S69: - | T69: - | U69: - | V69: 46237 | W69: 46282 | AA69: 5 | AD69: OK | AE69: OK | AF69: OK | AG69: 2026 | AH69: AB+ | AI69: JACKELINE JAFFAL - 015.187.900-11 - JAKE_JADDOU@HOTMAIL.COM | AJ69: - | AK69: R. PALESTINA, NAÇÕES | AL69: BC
E70: =SUMPRODUCT((AB70:AL70<>"")*(AB70:AL70<>"-")) -> 8 | F70: RAYAN GHAITH | G70: OK | H70: TURMA 7 (TARDE) | I70: =INT((TODAY()-J70)/365.25) -> 12 | J70: 41699 | K70: 120.406.541-19 | L70: 46237 | M70: 3 | N70: 47 8880-8849 | O70: - | P70: - | Q70: - | R70: - | S70: - | T70: - | U70: - | V70: 46237 | W70: 46282 | AA70: 5 | AD70: OK | AE70: OK | AF70: OK | AG70: 2026 | AH70: AB+ | AI70: JACKELINE JAFFAL - 015.187.900-11 - JAKE_JADDOU@HOTMAIL.COM | AJ70: - | AK70: R. PALESTINA, NAÇÕES | AL70: BC
E71: =SUMPRODUCT((AB71:AL71<>"")*(AB71:AL71<>"-")) -> 0 | F71: RICARDO TERESKOVAC | H71: TURMA 2 (MANHÃ) | I71: =INT((TODAY()-J71)/365.25) -> 9 | J71: 42912 | K71: 134.247.899-17 | L71: - | O71: - | P71: - | Q71: - | R71: - | S71: - | T71: - | U71: - | V71: - | W71: 46268 | AA71: 5
E72: =SUMPRODUCT((AB72:AL72<>"")*(AB72:AL72<>"-")) -> 4 | F72: VICENTE MARQUES DA SILVA | G72: OK | H72: TURMA 7 (TARDE) | I72: =INT((TODAY()-J72)/365.25) -> 13 | J72: 41522 | K72: 113.480.279-08 | L72: 46163 | M72: 2 | N72: MÃE: 47 9 9996 2393 PAI: 47 9 9670 9314 | O72: - | P72: - | Q72: - | R72: 46163 | S72: 46163 | T72: 46163 | U72: 46163 | V72: 46163 | W72: 46163 | X72: 46163 | Y72: 46163 | Z72: 46163 | AA72: 5 | AI72: MÁRIO FERNANDO - 981.854.629-68 - mariofernado@hotmail.com | AJ72: ROGÉRIO L. KUHNEN | AK72: R. JERUSALÉM - N 1581, SANTA REGINA | AL72: CAMBORIÚ
E73: =SUMPRODUCT((AB73:AL73<>"")*(AB73:AL73<>"-")) -> 3 | F73: VICTOR WILLIAN NEUCAMP | G73: OK | H73: TURMA 8 (TARDE) | I73: =INT((TODAY()-J73)/365.25) -> 13 | J73: 41499 | K73: 117.719.019-26 | L73: 46244 | N73: 47999020352 | O73: - | P73: - | Q73: - | R73: - | S73: - | T73: - | U73: - | V73: 46244 | W73: 46294 | AA73: 15 | AD73: OK | AE73: OK | AF73: OK
B74: X | C74: JUNHO | E74: =SUMPRODUCT((AB74:AL74<>"")*(AB74:AL74<>"-")) -> 6 | F74: VITOR HICHMEH | G74: OK | H74: TURMA 7 (TARDE) | I74: =INT((TODAY()-J74)/365.25) -> 10 | J74: 42472 | K74: 126.059.239-16 | L74: 46049 | M74: 3 | N74: PAI :11 98638-072 | O74: 46049 | P74: 46049 | Q74: 46049 | R74: 46049 | S74: 46049 | T74: 46049 | U74: 46246 | V74: 46246 | W74: 46246 | X74: 46246 | Y74: 46246 | Z74: 46246 | AA74: 10 | AD74: OK | AH74: AB+ | AI74: VINICIUS SALEH HICHMEH - 053.267.069-89 - VICIOSALEH@GMAIL.COM | AJ74: ANGLO | AK74: R. 3618 - N° 60, CENTRO BC | AL74: BC
B75: FALTA | E75: =SUMPRODUCT((AB75:AL75<>"")*(AB75:AL75<>"-")) -> 11 | F75: YAN CHISTOPHER MACHADO PEREIRA | G75: OK | H75: TURMA 7 (TARDE) | I75: =INT((TODAY()-J75)/365.25) -> 10 | J75: 42350 | K75: 13361787955 | L75: 46100 | M75: 3 | N75: 47999714705 | O75: - | P75: - | Q75: 46100 | R75: 46150 | S75: 46196 | T75: 46196 | U75: 46218 | V75: 46253 | W75: 46288 | AA75: 20 | AB75: 2026 | AC75: OK | AD75: OK | AE75: OK | AF75: OK | AG75: 2026 | AH75: O+ | AI75: ANA PAULA MACHADO | AJ75: CAIC | AK75: RUA -MONTE CORCOVADO | AL75: CAMBORIÚ
E76: =SUMPRODUCT((AB76:AL76<>"")*(AB76:AL76<>"-")) -> 6 | F76: YURI SANTOS RODRIGUES | G76: OK | H76: TURMA 8 (TARDE) | I76: =INT((TODAY()-J76)/365.25) -> 14 | J76: 41026 | K76: 600.531.930-24 | L76: 46303 | M76: 1 | N76: 47991245027 47992923532 | O76: - | P76: - | Q76: - | R76: - | S76: - | T76: - | U76: - | V76: - | W76: - | AA76: 10 | AD76: OK | AE76: OK | AG76: 2026 | AI76: - | AJ76: EBM LUCINIRA MELO REBELLO | AK76: RUA RIO CAMAUNÁ, 97 | AL76: CAMBORIÚ
E77: =SUMPRODUCT((AB77:AL77<>"")*(AB77:AL77<>"-")) -> 0
E78: =SUMPRODUCT((AB78:AL78<>"")*(AB78:AL78<>"-")) -> 0
E79: =SUMPRODUCT((AB79:AL79<>"")*(AB79:AL79<>"-")) -> 0
E80: =SUMPRODUCT((AB80:AL80<>"")*(AB80:AL80<>"-")) -> 0
E81: =SUMPRODUCT((AB81:AL81<>"")*(AB81:AL81<>"-")) -> 0
E82: =SUMPRODUCT((AB82:AL82<>"")*(AB82:AL82<>"-")) -> 0
E83: =SUMPRODUCT((AB83:AL83<>"")*(AB83:AL83<>"-")) -> 0
E84: =SUMPRODUCT((AB84:AL84<>"")*(AB84:AL84<>"-")) -> 0
E85: =SUMPRODUCT((AB85:AL85<>"")*(AB85:AL85<>"-")) -> 0
E86: =SUMPRODUCT((K86:AK86<>"")*(K86:AK86<>"-")) -> 0
E87: =SUMPRODUCT((K87:AK87<>"")*(K87:AK87<>"-")) -> 0
E88: =SUMPRODUCT((K88:AK88<>"")*(K88:AK88<>"-")) -> 0
E89: =SUMPRODUCT((K89:AK89<>"")*(K89:AK89<>"-")) -> 0
E90: =SUMPRODUCT((K90:AK90<>"")*(K90:AK90<>"-")) -> 0
E91: =SUMPRODUCT((K91:AK91<>"")*(K91:AK91<>"-")) -> 0
E92: =SUMPRODUCT((K92:AK92<>"")*(K92:AK92<>"-")) -> 0
E93: =SUMPRODUCT((K93:AK93<>"")*(K93:AK93<>"-")) -> 0
E94: =SUMPRODUCT((K94:AK94<>"")*(K94:AK94<>"-")) -> 0
E95: =SUMPRODUCT((K95:AK95<>"")*(K95:AK95<>"-")) -> 0
E96: =SUMPRODUCT((K96:AK96<>"")*(K96:AK96<>"-")) -> 0
E97: =SUMPRODUCT((K97:AK97<>"")*(K97:AK97<>"-")) -> 0
... E200: =SUMPRODUCT((K200:AK200<>"")*(K200:AK200<>"-")) -> 0

Sheet OUT
E1: CAIXA ESCOLINHA OUTUBRO 2026
A2: DATA | B2: ENTRADA | C2: SAÍDA | D2: TIPO | E2: REFERÊNCIA | F2: TIPO
A3: 46300 | B3: 300 | D3: PIX | E3: MIGUEL CORREIA - MENSALIDADE | F3: MENSALIDADE | G3: TOTAL DE ENTRADA | H3: TOTAL DE SAÍDA | I3: FATURAMENTO MENSAL
A4: 46300 | B4: 350 | D4: PIX | E4: ARTHUR HINCKEL DALLAGNO - MENSALIDADE SETEMBRO | F4: MENSALIDADE | G4: =SUM(B3:B50) -> 4437 | H4: =SUM(C3:C42) -> 0 | I4: =G4-H4 -> 4437
A5: 46301 | B5: 350 | D5: PIX | E5: HIROYUKI - MENSALIDADE | F5: MENSALIDADE
A6: 46302 | B6: 332 | D6: DÉBITO | E6: DAVI E SARA FONSECA BEUTING - MENSALIDADE | F6: MENSALIDADE
A7: 46303 | B7: 230 | D7: PIX | E7: LUCAS FERNANDO DELAGNELLO - MENSALIDADE | F7: MENSALIDADE
A8: 46303 | B8: 85 | D8: DINHEIRO | E8: BERNARDO BUENO DE ALBURQUERQUE - CALÇÃO E MEIÃO | F8: UNIFORME
A9: 46303 | B9: 225 | D9: DINHEIRO | E9: BERNARDO BUENO DE ALBURQUERQUE - MENSALIDADE | F9: MENSALIDADE
A10: 46303 | B10: 250 | D10: PIX | E10: DANIEL ELIAS - MENSALIDADE SETEMBRO | F10: MENSALIDADE
A11: 46304 | B11: 250 | D11: DINHEIRO | E11: JOHN ADAMS - MENSALIDADE | F11: MENSALIDADE
A12: 46304 | B12: 65 | D12: CREDITO | E12: JOHN ADAMS - CALÇÃO | F12: UNIFORME
A13: 46304 | B13: 140 | D13: DÉBITO | E13: JOÃO GERGENSLEY LAGUERRE - MENSALIDADE | F13: MENSALIDADE
A14: 46304 | B14: 110 | D14: DINHEIRO | E14: JOÃO GERGENSLEY LAGUERRE - MENSALIDADE | F14: MENSALIDADE
A15: 46304 | B15: 350 | D15: PIX | E15: GUILHERME PEREIRA DOS SANTOS - MENSALIDADE SETEMBRO | F15: MENSALIDADE
A16: 46304 | B16: 350 | D16: PIX | E16: GUILHERME PEREIRA DOS SANTOS - MENSALIDADE OUTUBRO | F16: MENSALIDADE
... A20: 46308 | B20: 250 | D20: PIX | E20: CICERO DE CASTRO DAPIEVE - MENSALIDADE OUTUBRO | F20: MENSALIDADE
G28: UNIFORMES: | H28: =SUM(B28,B40,B44) -> 0
G29: MENSALIDADES: | H29: =SUM(B3:B15,B17:B20,B23:B27,B29:B33,B35:B39,B42:B43,B45:B48) -> 4087
G30: OUTROS: | H30: =SUM(B22,B21,B16,B34,B41) -> 350
G32: TOTAL | H32: =SUM(H28:H30) -> 4437

Sheet DEVEDORES
A1: =SUMPRODUCT((X1:AG1<>"")*(X1:AG1<>"-")) -> 10 | B1: ANTONIO BLANCO GARCIA ROSA | C1: OK | D1: TURMA 2 (MANHÃ) | E1: =INT((TODAY()-F1)/365.25) -> 12 | F1: 41831 | G1: 047.286.990-64 | H1: 46051 | I1: 2 | J1: MÃE: 47 9 9243 5719 PAI: 47 9 9249 9441 | K1: - | L1: 46063 | M1: 46097 | N1: ESTÁ DESEMPREGADO, VAI TENTAR PAGAR | S1: IRÁ RETORNAR APENAS QUANDO PAGAR | W1: 10 | X1: 45539 | Y1: 45602 | Z1: ok | AA1: OK | AB1: OK | AC1: 01/01/2025 | AD1: O+ | AE1: JAQUELINE FLORES BLANCO - 899.584.030-72 - JAQUE_BLANCO@YAHOO.COM.BR | AF1: ARTUR SICHMANN | AG1: R. JOAQUIM AGOSTINHO VIEIRA - N 800, CENTRO | AH1: CAMBORIÚ
B5: Aluno | C5: Meses em aberto | D5: Qtd. meses | E5: Valor por mês (R$) | F5: Total devido (R$) | G5: Status | H5: Data da cobrança | I5: Observações
B6: Antonio Blanco Garcia Rosa | C6: Maio, Junho, Julho, Agosto | D6: 4 | G6: EM ABERTO | I6: ALUNO NÃO VEIO MAIS, PAI NÃO RESPONDE
B7: Davi de Souza Seben | C7: Julho, Agosto | D7: 2 | G7: FALTA 50,00 | I7: MÃE FRATUROU O PÉ (PAGAM EM DINHEIRO)
B8: Gabriel Queiróz Withoft | C8: Agosto | D8: 1 | G8: EM ABERTO | I8: VAI PAGAR SEMANA Q VEM (cobrar 08/09)
B9: Kaleb Felipe | C9: Abril, Maio, Junho, Julho, Agosto | D9: 5 | G9: EM ABERTO | I9: DIZ QUE ESTÁ EM UMA SITUAÇÃO DIFICIL E JÁ PAGOU ABRIL E MAIO (MAS NÃO TEM COMPROVANTE)
B10: João Victor Micheletti Rohrs | C10: Agosto | D10: 1 | G10: EM ABERTO | I10: Diz que virá fazer o pagamento

Sheet Observação
A1: MICHAEL NUNES BARBOSA | C1: MÃE: 47 99919 8226 PAI: 47 99993 9400 | P1: 12 | Q1: OK | R1: 8459161 | T1: 45672 | U1: OK | V1: OK | W1: --- | X1: 3° TRI 2024 | Y1: --- | Z1: 42335 | AA1: 2 | AB1: ROSILENI COSTA NUNES BARBOSA - 069.778.099-65 - MKCABECEIRAS@HOTMAIL.COM | AC1: SALESIANO | AD1: R. BERLIM - 115, SANTA REGINA
A2: OTÁVIO AUGUSTUS TONIOLO | C2: MÃE: 47 99638 1225 PAI: 41 99877 0608 | P2: 10 | Q2: OK | R2: 132.149.629-06 | S2: ok | U2: OK | V2: --- | W2: -- | X2: AT DE FREQUENCIA | Y2: --- | Z2: 42803 | AA2: 2 | AB2: D' PERUT BEAUTY EIRELI - 39611288/0001-76 - debysab@hotmail.com | AC2: CECAN | AD2: AV. RESINDO PAVAN - N 3177, ESTALEIRO
A3: JOSEP BONK BUSNELLO | C3: MÃE: 47 99999 8967 PAI: 47 99962 9402 | P3: 24 | Q3: OK | R3: 122.257.609-00 | S3: 45484 | T3: 45484 | V3: OK | W3: OK | X3: 2025 1 | Y3: O+ | Z3: 41824 | AA3: 4 | AB3: SIMONE ISABEL BONK BUSNELLO - 024.277.949-29 - ADVBONKBUSNELLO@GMAIL.COM | AC3: COC | AD3: R. 1926 - N 489, CENTRO
Y4: 42484 | Z4: 2 | AA4: MAURI A. GARCIA - 036.883.919-26 - MENDESGONCALVESLUCAS.@GMAIL.COM | AB4: DOMINGOS FONSECA | AC4: TEREZA EVANGELISTA GONÇALVES - 398, TABOLEIRO
A6: Pedir documenação começar pelo debaixo
A7: KALEB FELIPE | B7: 7
A8: DAVI LUCAS ZANELLA TONESER | B8: 6
A9: EDUARDO JOSÉ VAZ DE LIMA | B9: 6
A10: HENRI CARPENEDO DOS SANTOS | B10: 6
A11: HIROYUKI MOTA TUKAMOTO | B11: 6
A12: LEONARDO DAVI PEREIRA ROGAL | B12: 6
A13: MIGUEL CORREIA DE FREITAS | B13: 6
A14: NICOLLAS HIAN ALVES MARTINS | B14: 6
A15: AYLA G. MELLO SHFFNAN | B15: 5
A16: GABRIEL OSÓRIO GUEDES | B16: 5
A17: PEDRO DAVI LOCH | B17: 5
A18: PIETRO RIFFEL COUTO | B18: 5
... A25: LORENZO PERONIO ZAMBELE | B25: 0
A29: Avisar que estamos cancelando o Lep App
A30: PEDRO KREHNKE DE OLIVEIRA
A31: JOAO PEDRO MENEZES KNECHTEL
A32: MIGUEL PACHECO DO NASCIMENTO
A33: GABRIEL TALES MENOTTI
A34: DAVI DE SOUZA SEBEN
A35: HIROYUKI MOTA TUKAMOTO
A36: CARLOS PYETRO MATOS DE SOUZA
A37: ANTONIO BLANCO GARCIA ROSA
A38: JOHN ADAMS NERVARD
A39: JOÃO VICTOR MICHELETTI ROHRS

Sheet JUSTIFICATIVA DE FALTA
A2: NOME | B2: TURMA | C2: DATA | D2: CPF | E2: MOTIVO | G2: NOME | H2: TURMA | I2: DATA | J2: CPF | K2: MOTIVO
A3: THOMAS GERALDO DO CARMO | C3: 46256 | E3: MACHUCOU O PÉ, TEM ATESTADO DE 7 DIAS | G3: THOMAS GERALDO DO CARMO | I3: 46273 | K3: Thomas acordou com bastante dor barriga não vai conseguir treinar hoje

Sheet RETORNOS
A1: BERNARDO MARTINS DIETRICH BUENO | C1: MÃE: 47 9 9609 2686 PAI: 47 9 9782 8988 | D1: s | P1: 31 | Q1: OK | R1: 136.724.859-00 | S1: 45623 | T1: OK | U1: OK | V1: OK | W1: OK | X1: 2025 1 | Y1: O+ | Z1: 42264 | AA1: 2 | AB1: ISABELE CRISTINA DIETRICH - 056.494.439-47 - BELDIETRICH26@GMAIL.COM | AC1: DOMINGOS FONSECA | AD1: R. CEREJEIRA - N 957, TABULEIRO
A2: THOMAS GERALDO DO CARMO | B2: MÃE:47 999415473 PAI:47 996116633 | H2: 10 | I2: OK | J2: 053.034.669-90 | K2: 45729 | M2: OK | N2: OK | O2: OK | P2: 2025 1 | Q2: O- | R2: 42919 | S2: 4 | T2: AMARILDO HENRIQUE FRANCISCO - 053.034.669-90 - HENNRIQUE.CHICO@GMAIL.COM | U2: NEI PÃO E MEL | V2: R. MONTE BONETE - N 400, MONTE ALEGRE

Sheet DESATIVADOS
B1: NOME
B2: HENRY MACHADO LEIVAS | D2: 45714
C3: VENCIMENTO | D3: RG | E3: RESIDÊNCIA | F3: ATESTADO | G3: VACINAÇÃO | H3: SUS | I3: BOLETIM | J3: TIPO SANGUÍNEO | K3: NASCIMENTO | L3: ELETROCARDIOGRAMA | M3: DIAS | N3: FICHA
C4: 5 - 300 | D4: 86185985004 | K4: 40093 | M4: 4 | N4: OK
C5: DADOS FISCAIS: CLAUDIA FERNANDA DA SILVA MACHADO - 909.058.570-20 - CBELLA77@YAHOO.COM.BR
B6: LUIZ GUILHERME DA SILVA | C6: 45674 | D6: 45706
C7: VENCIMENTO | D7: RG | E7: RESIDÊNCIA | F7: ATESTADO | G7: VACINAÇÃO | H7: SUS | I7: BOLETIM | J7: TIPO SANGUÍNEO | K7: NASCIMENTO | L7: ELETROCARDIOGRAMA | M7: DIAS | N7: FICHA
C8: 15 | D8: 13396135903 | E8: OK | G8: OK | H8: OK | I8: 3° TRI 2024 | K8: 42898 | M8: 3 | N8: OK
C9: DADOS FISCAIS: LUIZ CARLOS DA SILVA - 895.988.739-00 - SILVAKLUIS@GMAIL.COM
B10: VITOR HICHMEH (MUDOU DE ESTADO) | C10: 45698 | D10: 45733 | E10: 45762
C11: VENCIMENTO | D11: RG | E11: RESIDÊNCIA | F11: ATESTADO | G11: VACINAÇÃO | H11: SUS | I11: BOLETIM | J11: TIPO SANGUÍNEO | K11: NASCIMENTO | L11: ELETROCARDIOGRAMA | M11: DIAS | N11: FICHA
C12: 10 - 250 | D12: 12605923916* | F12: 45496 | G12: OK | K12: 42472 | L12: 45496 | M12: 3 | N12: OK
C13: DADOS FISCAIS: VINICIUS SALEH HICHMEH - 053.267.069-89 - KELE_LEAL@YAHOO.COM.BR
B14: VICENZO VITORINO BANDEIRA FRANCO Encerrei porque não tive retorno da direção, senti desatenção e desigualdade no valor pago em relação às aulas | C14: 45671 | D14: 45698 | E14: 45727 | F14: 45755 | G14: 45785
C15: VENCIMENTO | D15: RG | E15: RESIDÊNCIA | F15: ATESTADO | G15: VACINAÇÃO | H15: SUS | I15: BOLETIM | J15: TIPO SANGUÍNEO | K15: NASCIMENTO | L15: ELETROCARDIOGRAMA | M15: DIAS | N15: FICHA
C16: 15 | D16: 12198734974 | E16: OK | J16: AB+ | K16: 41686 | M16: 2 | N16: OK
C17: DADOS FISCAIS: ANTONIO CARLOS BANDEIRA FRANCO - 088.833.478-89 - BANDEIRA@BANDEIRAFRANCO.COM.BR
B18: GABRIEL THIBES FILHO | C18: -------- | D18: 45706
C19: VENCIMENTO | D19: RG | E19: RESIDÊNCIA | F19: ATESTADO | G19: VACINAÇÃO | H19: SUS | I19: BOLETIM | J19: TIPO SANGUÍNEO | K19: NASCIMENTO | L19: ELETROCARDIOGRAMA | M19: DIAS | N19: FICHA
C20: 5 | D20: 11676695923 | E20: OK | F20: 45705 | J20: A+ | K20: 41906 | M20: 2 | N20: OK
C21: DADOS FISCAIS: GABRIEL THIBES - 058.802.369-86 - GABRIELTHIBES89@GMAIL.COM
B22: LUCAS COLETTO ROLIM | D22: 45708 | E22: 45708 | F22: 45708 | G22: 45708 | H22: 45708 | I22: 45708 | P22: UNIFICADO
C23: VENCIMENTO | D23: RG | E23: RESIDÊNCIA | F23: ATESTADO | G23: VACINAÇÃO | H23: SUS | I23: BOLETIM | J23: TIPO SANGUÍNEO | K23: NASCIMENTO | L23: ELETROCARDIOGRAMA | M23: DIAS | N23: FICHA | O23: MÃE: 47 9 9156 7250
C24: 5 | D24: 8048065 | F24: 45699 | K24: 41024 | L24: 45685 | M24: 2 | N24: OK | O24: PAI: 47 9 9117 8217 | P24: ENDEREÇO:
C25: DADOS FISCAIS: DANIELE FORTES COLETTO - 930.875.000-20 - | P25: R. 3130 - 112, CENTRO
C26: ------- | D26: -------- | E26: -------- | F26: 45764 | G26: 45824
C27: VENCIMENTO | D27: RG | E27: RESIDÊNCIA | F27: ATESTADO | G27: VACINAÇÃO | H27: SUS | I27: BOLETIM | J27: TIPO SANGUÍNEO | K27: NASCIMENTO | L27: ELETROCARDIOGRAMA | M27: DIAS | N27: FICHA | O27: MÃE: 43 99606 8677 | P27: ANGLO
C28: 10 | D28: 8475844 | E28: OK | G28: OK | H28: NÃO TEM | J28: O+ | K28: 42529 | L28: 45757 | M28: 2 | N28: OK | O28: PAI: 44 92003 7409
B29: RAFAEL MORAIS SETÚBAL (MUDOU DE ESTADO) | C29: DADOS FISCAIS: RAONI PEREIRA FONSECA SILVA SETÚBAL - 002.630.721-93 - RAONI.TRB@GMAIL.COM
B30: JOÃO PAULO DE OLIVEIRA PAVAN (MUDOU DE ESTADO) | C30: 45674 | D30: 45756 | E30: 45770 | P30: ANGLO
C31: VENCIMENTO | D31: RG | E31: RESIDÊNCIA | F31: ATESTADO | G31: VACINAÇÃO | H31: SUS | I31: BOLETIM | J31: TIPO SANGUÍNEO | K31: NASCIMENTO | L31: ELETROCARDIOGRAMA | M31: DIAS | N31: FICHA | O31: MÃE: 47 99653 0400
C32: 20 | D32: 12590446969 | E32: OK | H32: --- | I32: 3° TRI 2024 | K32: 42416 | M32: 3 | N32: OK | O32: PAI: 47 99668 6503 | P32: ENDEREÇO:
C33: DADOS FISCAIS: PAULIANA FERREIRA DE OLIVEIRA - 960.071.761-34 - PAULIANAPAVAN@GMAIL.COM | P33: R. 951 - N 41, CENTRO
B34: BERNARDO CAVALHEIRODE MEDEIROS RIBEIRO (valor da mensalidade) | E34: 45715 | F34: 45755 | P34: CLOTILDE
C35: VENCIMENTO | D35: CPF | E35: RESIDÊNCIA | F35: ATESTADO | G35: VACINAÇÃO | H35: SUS | I35: BOLETIM | J35: TIPO SANGUÍNEO | K35: NASCIMENTO | L35: ELETROCARDIOGRAMA | M35: DIAS | N35: FICHA | O35: MÃE: 47 9 9723 0613
C36: 5 | D36: 61.294.650-92 | E36: OK | G36: OK | H36: OK | K36: 43479 | M36: 2 | N36: OK | O36: PAI: 47 9 8800 5989 | P36: ENDEREÇO
C37: DADOS FISCAIS: MATHEUS DE MEDEIROS - 019.476.320-00 - MEDEIROS220214@GMAIL.COM | P37: R. AMAZONAS - N 19, CENTRO
B38: BRAYAN KUSSEK MULLER | C38: -------- | D38: -------- | E38: -------- | F38: 45748 | G38: 45783
C39: VENCIMENTO | D39: RG | E39: RESIDÊNCIA | F39: ATESTADO | G39: VACINAÇÃO | H39: SUS | I39: BOLETIM | J39: TIPO SANGUÍNEO | K39: NASCIMENTO | L39: ELETROCARDIOGRAMA | M39: DIAS | N39: FICHA
C40: 5 | D40: 8117047 | E40: OK | F40: 45742 | G40: OK | H40: OK | I40: ATESTADO DE FREQUENCIA | J40: O+ | K40: 41870 | M40: 2 | N40: OK
C41: DADOS FISCAIS: AKIELLI KUSSEK - 061.422.719-48 - AKIELLIKUSSEK@GMAIL.COM
B42: KALEB GONÇALVES DE ANDRADE ( SAIU POIS ESTAVA EM TRATAMENTO DE ASMA, QUANDO VOLTOU NÃO QUIS TREINAR) | C42: -------- | D42: -------- | E42: -------- | F42: 45747 | G42: -- | H42: -- | I42: 45845 | P42: AQUARELA DO SABER
C43: VENCIMENTO | D43: RG | E43: RESIDÊNCIA | F43: ATESTADO | G43: VACINAÇÃO | H43: SUS | I43: BOLETIM | J43: TIPO SANGUÍNEO | K43: NASCIMENTO | L43: ELETROCARDIOGRAMA | M43: DIAS | N43: FICHA | O43: MÃE: 47 99964 0854
C44: 5 | D44: 15823258984 | E44: OK | F44: 45741 | G44: OK | H44: OK | J44: O+ | K44: 44223 | L44: 45741 | M44: 1 | N44: OK | O44: PAI: 47 99674 0535 | P44: ENDEREÇO:
C45: DADOS FISCAIS: LEONARDO ANDRADE - 095.346.099-19 - leonardo_andrade2@hotmail.com | P45: R. MONTE MERU - 700, CONDE VILA VERDE
B46: LUCCA CARVALHO MISITI (MÃE TIROU POR CONTA DAS NOTAS BAIXAS) | C46: --- | D46: --- | E46: 45748 | F46: 45406 | G46: 45785 | H46: 45819 | P46: LICEU
C47: VENCIMENTO | D47: RG | E47: RESIDÊNCIA | F47: ATESTADO | G47: VACINAÇÃO | H47: SUS | I47: BOLETIM | J47: TIPO SANGUÍNEO | K47: NASCIMENTO | L47: ELETROCARDIOGRAMA | M47: DIAS | N47: FICHA | O47: MÃE: 47 9 9639 2995
C48: 10 | D48: 13631291981 | E48: OK | G48: OK | H48: OK | I48: ATESTADO DE FREQUENCIA | J48: A+ | K48: 41191 | M48: 2 | N48: OK | O48: PAI: 47 9 9785 3586 | P48: ENDEREÇO:
C49: DADOS FISCAIS: THIAGO MISITI DOS SANTOS - 376.363.548-37 - TMISITI@HOTMAIL.COM | P49: R. ARMAZÉM - N 593, MUNICIPIOS
B50: LAURA VITÓRIA DA SILVA MATTIA (NÃO QUIS MAIS TREINAR, POR CONTA DOS MENINOS) | C50: ------- | D50: ------- | E50: ------- | F50: ------- | G50: 45786 | P50: DOMINGOS FONSECA
C51: VENCIMENTO | D51: RG | E51: RESIDÊNCIA | F51: ATESTADO | G51: VACINAÇÃO | H51: SUS | I51: BOLETIM | J51: TIPO SANGUÍNEO | K51: NASCIMENTO | L51: ELETROCARDIOGRAMA | M51: DIAS | N51: FICHA | O51: MÃE: 47 9 9930 1512
C52: 10 | D52: 125.534.759.77 | E52: ok | H52: ok | I52: AT. FREQUENCIA | J52: A+ | K52: 41988 | L52: OK | M52: 3 | N52: OK | O52: TIAGO (PADRASTO): 47 9 9141 0389 | P52: ENDEREÇO:
C53: DADOS FISCAIS: DJENIFER ANDRESSA DA SILVA - 082.769.809-70 - djeniferandressa@gmail.com | P53: R. LEANDRO BERTOLDI - N 191, CEDROS
B54: PEDRO ROSKOSKI PANDINI (saiu pois esta Treinando em camboriú) | C54: VENCIMENTO | D54: 45708 | E54: 45736 | F54: 45772 | G54: 45792 | H54: 45828 | I54: 45883 | J54: 45904 | K54: NASCIMENTO | L54: ELETROCARDIOGRAMA | M54: DIAS | N54: FICHA | O54: MÃE: 47 99684 0505 | P54: ESCOLA
B55: EDUARDO PUGATSCH JUNIOR | C55: MÃE: 47 9 8463 6027 PAI: 47 9 8481 5389 | E55: 45713 | F55: 45741 | G55: 45772 | I55: -------- | P55: OK | Q55: 4359063059* | S55: 15 | T55: 45667 | U55: OK | Z55: 41592 | AA55: 3 | AB55: EDUARDO PUGATSCH - 767.565.050-68 - EDUARDO.PUG3@GMAIL.COM | AC55: LICEU CATARINENSE | AD55: R. AGROLÂNDIA - 813, IATE CLUBE
B56: ENZO GABRIEL ALVES COUTO | C56: MÃE: -- PAI: 47 9 8913 4934 | D56: 45695 | E56: 45736 | F56: 45777 | G56: 45777 | H56: 45873 | I56: 45873 | P56: OK | S56: 10 - 400 | Z56: 41913 | AA56: 2 | AB56: DIONATA ALVES COUTO - 025.082.320-92 - COUTODIONATA22@GMAIL.COM | AC56: ENERGIA | AD56: R. 3144 - N 246, CENTRO
B57: ENZO MATHEUS TEIXEIRA SIQUEIRA | C57: MÃE: 92 9 9192 0813 PAI: 21 9 9269 6621 | D57: -------- | E57: -------- | F57: -------- | G57: ------- | H57: 45779 | P57: OK | Q57: 704.096.622-08 | S57: 10 | U57: OK | V57: OK | Y57: O+ | Z57: 41208 | AA57: 3 | AB57: DADOS FICAIS: JOSIMARA GOMAS TEIXEIRA SIQUEIRA - 961.878.242-53 - agilaluminio@gmail.com | AC57: IVONE | AD57: R. DAMASCO - N 84, SANTA REGINA
B58: ESTEVÃO RIBAS | C58: MÃE: 47 99949 5357 PAI: 47 99648 5769 | D58: - | E58: - | F58: -- | G58: --- | H58: -- | I58: -- | J58: -- | K58: -- | L58: 45924 | P58: OK | Q58: 139.916.449-31 | S58: 10 | T58: 45838 | U58: OK | X58: 2025 2° BI | Y58: O+ | Z58: 42576 | AA58: 1 | AB58: REUEL RIBAS - 005.673.329-18 - RIBASREUEL@GMAIL.COM | AC58: CEM GHISLANDI | AD58: R. DOM MARCOS - 352, IATE CLUBE
B59: EUCLIDES DOS SANTOS SIQUEIRA DA SILVA FILHO | C59: MÃE: 47 9 9185 3808 PAI: 47 9 9124 1295 | D59: 45681 | E59: 45727 | F59: 45757 | G59: 45787 | H59: 45819 | I59: 45849 | J59: 45884 | K59: 45910 | P59: OK | Q59: 053.329.252-20 | S59: 10 - 270 | W59: OK | Z59: 40843 | AA59: 3 | AB59: EUCLIDES DOS SANTOS SIQUEIRA DA SILVA - 626.557.102-82 - JOSIETESILVAHK@GMAIL.COM | AC59: ALCUINO | AD59: R. MONTE POUSO ALTO - N 614, MONTE ALEGRE
B60: JOAQUIM AGOSTINI | C60: MÃE: 47 99943 5913 PAI: 47 99963 2050 | D60: 45674 | E60: 45702 | F60: 45729 | G60: 45762 | H60: 45792 | I60: 45824 | J60: 45855 | K60: 45884 | P60: OK | Q60: 138.725.289-55 | S60: 15 | T60: 45532 | U60: OK | V60: OK | W60: OK | X60: 2025 1 | Y60: O- | Z60: 43118 | AA60: 3 | AB60: ELIONAI AGOSTINI - 105.305.409-24 - AGOSTINIGILDO@GMAIL.COM | AC60: DOMINGOS FONSECA | AD60: R. PINDAIBA - 234, TABULEIRO
B61: BRENO CURVELO FREITAS DIAS | C61: MÃE: 47 9 9709 2939 PAI: 47 9 9701 9582 | D61: ------- | E61: ---- | F61: ------- | G61: ------- | H61: ------ | I61: ----- | J61: 45880 | P61: OK | Q61: 142.237.649-42 | R61: 45870 | S61: 10 | T61: 45862 | U61: OK | V61: OK | W61: OK | X61: 2025 1 | Y61: A- | Z61: 43231 | AA61: 2 | AB61: JAILMA PATRICIA FREITAS DIAS - 039.642.914-98 - PATRICIAFREITAS4568@GMAIL.COM | AC61: TOMAZ FRANCISCO | AD61: R. BRUSQUE - N N 111, MUNICIPIOS
B62: CAIO DOS ANJOS | C62: MÃE: 47 9 9174 9450 PAI: 47 9 9119 1994 | D62: ------- | E62: ------- | F62: ------- | G62: ------- | P62: OK | S62: 13/16 | U62: ok | Y62: O- | Z62: 43797 | AA62: 3 | AB62: CRISTIAN DOS ANJOS SILVA - 089.154.149-77 - cristiian.caio@gmail.com | AC62: IVO SILVEIRA | AD62: R. MONTE SERRA NEGRA - N 261, MONTE ALEGRE
B63: JOAQUIM AUGUSTO BONAFIN | C63: MÃE: 47 9 9918 0869 PAI: 47 9 9202 2162 | P63: OK | S63: 5 | Z63: 43600 | AA63: 4 | AB63: AGUSTO Z. BONFIN - 024.540.820-71- GUTOBONFIM@GMAIL.COM | AC63: ASTER | AD63: R. PINDAIBA - N 31, TABULEIRO
B64: GABRIEL RODRIGUES CALDEIRA | C64: MÃE: 47 9 8889 9247 PAI: 47 9 8913 1232 | D64: -------- | E64: --------- | F64: 45734 | G64: 45776 | P64: OK | Q64: 14080481918 | S64: 15 | Y64: A+ | Z64: 43193 | AA64: 2 | AB64: MICHAEL GONÇÃLVES CALDEIRA - 049.699.499-99 - RODRIGUESCALDEIRAD@GMAIL.COM | AC64: ANGLO | AD64: R. ACILO GARCIA - N 252, CENTRO
B65: GABRIEL QUEIROZ WHITOF | D65: ------- | E65: ------- | F65: ------- | G65: ------- | H65: ----- | I65: ------ | J65: -- | K65: 45923 | P65: OK | Q65: 127.764.529-93 | R65: 45918 | S65: 10 | U65: OK | V65: OK | W65: OK | X65: 2025 1 | Z65: 42571 | AA65: 2 | AB65: BRUNA LETICIA QUEIROZ NITHOOT - 078.325.119-07 - LIVRARIAFAMILIA23@GMAIL.COM
B66: GREGORY MACHADO | C66: MÃE: 47 9 9957 4884 PAI: 47 9 9957 4883 | D66: 45687 | E66: 45722 | F66: 45740 | G66: 45757 | H66: 45813 | I66: 45841 | J66: 45888 | K66: 45888 | L66: 45917 | M66: 45944 | P66: OK | Q66: 137.234.839-50 | R66: 45352 | S66: 20 | T66: 45686 | U66: OK | V66: OK | W66: OK | X66: 3° TRI 2024 | Y66: O+ | Z66: 41247 | AA66: 4 | AB66: GIOVANI CARVALHO DOS SANTOS - 040.639.229-36 - GIOVANICARVALHO4558@GMAIL.COM | AC66: IVO SILVEIRA | AD66: R. MONTE PAMIR- 199, CONDE VILA VERDE
B67: IOHAN SOARES DOS SANTOS | C67: MÃE: 47 9 9674 0946 PAI: 47 99604 4694 | D67: ------- | E67: ------- | F67: ------- | G67: ------- | H67: --- | I67: --- | P67: OK | Q67: 113.327.979-11 | S67: 10 | U67: OK | V67: OK | X67: 1° TRI 2025 | Z67: 41680 | AA67: 3 | AB67: RAISSA MARTINS SOARES - 091.241.489-89 - RAISSA.MARTINSS@GMAIL.COM | AC67: IVO SILVEIRA | AD67: AV. SANTA CATRINA - 630, ESTADOS
B68: JOÃO SEVERINO DE OLIVEIRA NETO | E68: ------- | F68: ------- | G68: ------- | H68: 45803 | AA68: 2
B69: JOÃO VITOR RODRIGUES | C69: MÃE: 47 99786 6458 PAI: 47 99771 7696 | D69: ------- | E69: ------- | F69: ------- | G69: ------- | H69: 45799 | P69: OK | Q69: 127.809.319-22 | R69: 45919 | S69: 10 | U69: OK | V69: OK | W69: OK | Z69: 40806 | AA69: 2 | AB69: SABRINA - 060.159.039-29 - binaewag@gmail.com | AC69: CEM NOVA ESPERANÇA | AD69: R. JOSE FRANCISCO VETO - 274, BARRA
B70: JOSUE KEVIK CAVALCANTE | J70: ------- | K70: ------ | L70: ------ | M70: 45939 | P70: OK | Q70: 145.942.599.52 | S70: 10
B71: KALEB FELIPE | C71: MÃE: 47 99994 9026 PAI: 47 99932 5157 | D71: ------- | E71: ------- | F71: ------- | G71: ------- | H71: ---- | I71: ---- | J71: ----- | K71: ----- | P71: OK | Q71: 144.530.649-26 | R71: 45908 | S71: 20 | V71: OK | W71: .... | X71: AT DE FREQUENCIA | Y71: O+ | Z71: 43346 | AA71: 1 | AB71: JEFERSN WILIAN O. DA SILVA - 110.899.009-61 - WILIANJEFERSON1002@GMAIL.COM | AC71: DOMINGOS FONSECA | AD71: R. MONTE ORIZADA - 693, MONTE ALEGRE
B72: KELVIN MACKLAREN MEIRELES | D72: ------- | E72: ------- | F72: ------- | G72: ------- | H72: ------- | I72: ------- | J72: ------- | K72: ------- | L72: ------- | M72: ------- | N72: 45972 | P72: OK | Q72: 08161868204
B73: LEONARDO DECARLI BATISTA | C73: PAULA: 47 9 9117 2590 PAI: 47 9 9192 9968 | D73: ------- | E73: ------- | F73: ------- | G73: ------- | P73: OK | S73: 20 | Z73: 40639 | AA73: 2 | AB73: PAULO LUIZ DECARLI - 219.757.440-04 - paulo@dbsulrepresentacoes.com.br | AC73: COC | AD73: R. 2850 - N 470, CENTRO
B74: HEITOR RAMPANELLI CECILIO | C74: MÃE: 47 98405 6102 PAI: 47 98477 6479 | D74: ------- | E74: ------- | F74: ------- | G74: ------- | H74: --- | I74: --- | J74: --- | K74: --- | L74: 45916 | N74: 45979 | P74: OK | S74: 20 | V74: ok | W74: ok | Z74: 44211 | AA74: 4 | AB74: TAIS CIRSTINA RAMPANELLI - 007.511.000-80 - TAISC.RAMP@GMAIL.COM | AC74: JASON MANOEL PEREIRA | AD74: R. SERV. NILTON COELHO, BRAÇO
B75: GUSTAVO BRUNETTO | D75: ------- | E75: ------- | F75: ------- | G75: ------- | H75: ----- | I75: 45811 | J75: 45840 | K75: 45869 | L75: 45898 | M75: 45930 | N75: 45958 | Q75: 137.452.059-44 | R75: 45918 | S75: 1 | T75: OK | W75: OK | X75: 2025 1 | Z75: 43064 | AA75: 4
B76: VINICIUS ATAIDE FURTADO | C76: MÃE: 47 9 9693 5450 VITOR: 49 9 9951 8916 | D76: 45685 | E76: 45723 | F76: 45755 | G76: 45785 | H76: --- | I76: ----- | J76: --- | K76: 45890 | M76: 45939 | P76: OK | Q76: 013.404.109-74 | R76: 45337 | S76: 5 | T76: 45625 | V76: OK | W76: OK | Y76: O+ | Z76: 41170 | AA76: 2 | AB76: PATRÍCIA ATAIDE - 056.329.779-43 - PATYPATITAATAIDE@GMAIL.COM | AC76: IVO SILVEIRA | AD76: AV SANTA CATARINA - N 235, ESTADOS
B77: BENJAMIN ASHER DE ANDRADE ZAIN | C77: MÃE: 47 9 9677 1029 PAI: 47 9 9621 8377 | D77: -------- | E77: ------- | F77: ------- | G77: 45757 | H77: 45792 | I77: 45818 | J77: 45846 | K77: 45884 | P77: OK | Q77: 7304703 | R77: 45748 | S77: 10 | T77: 45748 | U77: OK | V77: OK | W77: OK | X77: 2025 1 | Y77: A+ | Z77: 41133 | AA77: 2 | AB77: MONIA RAQUEL T. DE ANDREDE ZAIN - 005.193.509-01 - MONIASC@HOTMAIL.COM | AC77: LICEU CATARINENSE | AD77: R. JOÃO BATISTA GANANCINI - N 112, LIDIA DUARTE
B78: GABRIEL HENRIQUE BRANCO DA SILVA | C78: MÃE: 11 9 8013 3943 PAI: 11 9 6209 0629 | D78: -------- | E78: -------- | F78: 45723 | G78: 45754 | H78: 45785 | I78: 45811 | J78: 45811 | K78: 45876 | L78: 45902 | M78: 45933 | N78: 45965 | P78: OK | Q78: 555.019.028-18 | R78: 45726 | S78: 7 | T78: 45726 | U78: OK | Z78: 41014 | AA78: 4 | AB78: DÉBORA ALVES BRANCO - 418.137.098-40 - DEBORAAAABRANCO@GMAIL.COM | AD78: R. OSVALDO MINELLA - 2029, CEDRO
B79: PIETRA DE SOUZA GALVAN | C79: MÃE: 47 98415 3092 PAI: 47 99171 8484 | I79: 23 | J79: OK | K79: 132.457.869-64 | L79: 45923 | M79: 45923 | N79: OK | Q79: 1 TRIMESTRE | R79: O + | S79: 42823 | T79: 2 | U79: JUCEMARA- 036.373.889-44 jucemarapaim@hotmail.com | V79: CECAN | W79: RUA IPORÃ Nº80 RIO PEQUENO
B80: JOAO MIGUEL PAIM | C80: mãe 47- 99174-9405 pai 47 992224438 | I80: 5 | J80: OK | K80: 8551737 | L80: 45715 | M80: 45715 | N80: OK | O80: OK | P80: OK | S80: 41180 | T80: 3 | U80: JEFFERSOM EDINEI DE OLIVEIRA - 038.077.089-01 - TIOJEFFERSOM1234@GMAIL.COM | V80: ANITA | W80: R. MONTE CARLO - N 224, MONTE ALEGRE
B81: ÁTILA TEIXEIRA DE OLIVEIRA | C81: MÃE: 47 9 9244 3456 PAI: 47 9 9255 4268 | I81: 17 | J81: OK | K81: 503.015.618-69 | N81: OK | O81: OK | P81: OK | R81: A+ | S81: 42285 | T81: 2 | U81: ANDRE MANFIN - 184.302.438-10 -andre.vendas. churrasqueiras@gmail.com | V81: CAIC | W81: R. CONCÓRDIA - N 35, MUNICIPIOS
B82: ARTHUR DE OLIVEIRA MANFRIN | C82: MÃE: 47 9 9620 2548 PAI: 47 9 9629 3963 | I82: 20 | J82: OK | K82: 145.499.869-56 | M82: OK | O82: OK | P82: UNIMED | Q82: 2025 2 | R82: O+ | S82: 43393 | U82: LUIZ FERNANDO DO CARMO - 017.952.420-86 - FERNANDO5128470@GMAIL.COM | V82: CECAM | W82: R.JUVÊNCIO DELFINO DA SILVA -124, NOVA ESP.
B83: THOMAS GERALDO DO CARMO | C83: MÃE:47 999415473 PAI:47 996116633 | I83: 10 | J83: OK | K83: 053.034.669-90 | L83: 45729 | N83: OK | O83: OK | P83: OK | Q83: 2025 1 | R83: O- | S83: 42919 | T83: 4 | U83: AMARILDO HENRIQUE FRANCISCO - 053.034.669-90 - HENNRIQUE.CHICO@GMAIL.COM | V83: NEI PÃO E MEL | W83: R. MONTE BONETE - N 400, MONTE ALEGRE
B84: CAIO DE SOUZA FRANCISCO | I84: 10 | J84: OK | K84: 145.231.389-07 | L84: 45866 | M84: 45884 | N84: OK | O84: OK | P84: OK | Q84: FREQUENCIA | R84: AB+ | S84: 43378 | T84: 4 | U84: LEONARDO LEVORATO BELINO - 061.138.239-38 -leonardolevorato@hotmail.com | V84: ARTHUR SICHMAN | W84: R. BASILIO PEDRO DA SILVA - N 126, CENTRO
A85: ABUT | B85: LEONARDO HENRIQUE DA SILVA LEVORATO | C85: MÃE: 42 9 9113 3107 PAI: 42 9 9266 0629 | I85: 20 | J85: OK | K85: 132.787.909-36 | L85: 45671 | M85: 45671 | N85: OK | P85: OK | Q85: 2025 1 | S85: 42842 | T85: 2 | U85: PRISCILLA FLENICK - 077.679.229-60 - PRI.FLENICK@HOTMAIL.COM | V85: RECRIARTE | W85: R. 1301 - 101, CENTRO
B86: FABRÍCIO FLENICK DE SOUZA | C86: MÃE: 47 9 9250 2231 PAI: 47 9 9949 4903 | I86: 15 | J86: OK | K86: 139.594.239-00 | L86: 45890 | M86: 45867 | N86: OK | O86: OK | P86: OK | Q86: 3° TRI 2024 | R86: O- | S86: 42549 | T86: 2 | U86: JULIANE DA SILVA - 05516601983 - JULIANE.SLV@ICLOUD.COM | V86: RECRIARTE | W86: R. CAÇADOR - 279, MUNICIPIUS
B87: ENZO GABRIEL DOS SANTOS | C87: MÃE: 47 9 9179 0345 PAI: 47 9 9122 0888 | I87: 10 | J87: OK | K87: 144.585.879-78 | N87: OK | O87: OK | P87: OK | Q87: 2025 1 | R87: A+ | S87: 42056 | T87: 2 | U87: LEONICE BARBOSA - 07172198956 - LEONICEBC@YAHOO.COM.BR | V87: DOMINGOS FONSECA | W87: R. SILVEIRA - N 450, TABULEIRO
B88: GUSTAVO FERNANDES BARBOSA | C88: MÃE: -- PAI: 47 9 9952 8703 | I88: 10 | J88: OK | K88: 154.475.499-06 | L88: 45679 | M88: 45679 | N88: OK | O88: OK | P88: OK | Q88: DECLARAÇÃO DE FRE. | R88: A+ | S88: 43881 | T88: 1 | U88: CAROLINE FRANCIELI DORVAL DA SILVA - 067.509.289-27 - CAROLDORVALBC@HOTMAIL.COM | V88: AQUARELA DO SABER | W88: R. DUBLI - N 153, SANTA REGINA
A89: devido aos horários | B89: LUCAS DORVAL DA SILVA | C89: MÃE: 47 9 9633 4084 PAI: 47 9 9615 7386 | J89: OK | K89: 137.214.829-99 | P89: OK | S89: 41248 | V89: C.E. VEREADOR SANTA | W89: R. PINDAÍBA N° 31, APTO 704 - TABOLEIRO
A90: incidente da maria eduarda | B90: INÁCIO CASTELLI BARDEN | C90: MÃE: 47 992441208 PAI: 47 991590898 | I90: 15 | J90: OK | K90: 136.513.029-03 | L90: 45574 | M90: 45574 | N90: OK | O90: OK | P90: OK | Q90: 2025 1 | R90: AB+ | S90: 43029 | T90: 3 | U90: ERVELINO JOÃO DA SILVA - 795.694.719-72 - ELENICE1928@GMAIL.COM | V90: DOMINGOS FONSECA | W90: R. GUARAMIRIM - 1301, TABULEIRO
B91: JOSÉ MIGUEL DA SILVA | C91: MÃE: 47 98447 3454 PAI: 47 99125 0508 | I91: 20 | J91: OK | K91: 145.846.459-81 | L91: 45910 | S91: 42580 | T91: 3 | U91: DANALIZ FREISTAUER PUHL - 007.080.640-35 - DANAFEISTAUES85@GMAIL.COM | V91: JOAQUIM VICENTE | W91: R. 420 - 634, MORRETES
A92: DEVE | B92: BERNARDO FEISTAUER PUHL | C92: MÃE: 47 99922 8682 PAI: 47 98834 7929 | I92: 7 | J92: OK | K92: 115.722.869-03 | L92: 45714 | M92: 45714 | N92: OK | O92: OK | P92: OK | Q92: 2025 1 | R92: O+ | S92: 41864 | T92: 2 | U92: FERNANDA MARIA VITORASSI ROSSINI - 028.977.359-88 - fernandamariavitoriarossini@gmail.com | V92: CECAM | W92: R. CEREJEIRA - 966, TABULEIRO
B93: SAMUEL LUIDGI VITORASSI ROSSINI | C93: MÃE: 47 98466 2891 PAI: 47 99952 9091 | I93: 1 | J93: OK | K93: 126.303.409-88 | L93: 45835 | M93: 45883 | P93: OK | S93: 42484 | T93: 2 | U93: MAURI A. GARCIA - 036.883.919-26 - MENDESGONCALVESLUCAS.@GMAIL.COM | V93: DOMINGOS FONSECA | W93: TEREZA EVANGELISTA GONÇALVES - 398, TABOLEIRO
B94: LUCAS MENDES GARCIA | C94: MÃE: 47 99673 8982 PAI: 47 99916 2589 | D94: 45909 | E94: 9/9/2025 talvez não venha mais | I94: 8 | J94: OK | K94: 138.464.239-04 | R94: O+ | S94: 41752 | T94: 3 | U94: BRUNA GERVASONI AYALA - 069.639459-69 - BRUNAGERVA@HOTMAIL.COM | V94: COC | W94: RUA CORONEL BENJAMIN VIEIRA - 635, CENTRO
B95: AUGUSTO GERVASONI PIVETTA | C95: MÃE: 47 99292 5737 RESPONSÁVEL: 47 9632 9500 | D95: 46044 | E95: 46061 | I95: 5 | J95: NÃO TEMOS | K95: 053.322.370-90 | Q95: 2025 1 | S95: 42723 | T95: 4 | U95: VIRGINIA OSÓRIO - 041.441.270-28 - OSÓRIO.VIRGINIA@GMAIL.COM | V95: ANGLO | W95: R. ALCILA GARCIA - N 252, CENTRO
B96: GABRIEL OSÓRIO GUEDES | C96: MÃE: 55 9 8453 4336 | D96: s | I96: 10 | J96: OK | K96: 135.339.899-41 | N96: OK | O96: OK | P96: OK | Q96: 2025 1 | S96: 42384 | T96: 2 | U96: GUILHERME MENEZES DE GOES DECANINI - 322.439.718-79 - GUILHERMEMEMGDECANINI@GMAIL.COM
B97: CAIO ODORIZZI DECANINI | C97: MÃE: 47 99620 3209 PAI: 47 99981 5278 | D97: s | I97: 10 | J97: OK | K97: 13841725996 | L97: 45918 | M97: 45695 | N97: OK | O97: OK | Q97: 3° TRI 2024 | S97: 43405 | T97: 2 | U97: LUCIENE ANGELICA DA SILVA - 033.751.596-41 - LUCIELEANGELICADASILVA@GMAIL.COM | V97: CAIC | W97: R. CHAPECO - 159, MUNICIPIOS
B98: LORENZO GABRIEL DOS SANTOS SILVA | C98: MÃE: 44 9 9912 7581 | D98: s | E98: - | I98: 10 | J98: OK | K98: 518.306.468-77 | L98: 45798 | M98: 45811 | N98: OK | O98: OK | P98: OK | Q98: MATRICULA | R98: A+ | S98: 42653 | T98: 2 | U98: PABLO CARVALHO FONSECA DOS SANTOS - 923.409.970-20 - pablocarvalho77@gmail.com
B99: LUCAS SABANAE FONSECA DOS SANTOS | C99: MÃE: 47 9 9779 4841 PAI: 47 9 9691 4841 | D99: 46051 | I99: 10 | J99: OK | K99: 132.149.629-06 | L99: ok | N99: OK | O99: --- | P99: -- | Q99: AT DE FREQUENCIA | S99: 42803 | T99: 2 | U99: D' PERUT BEAUTY EIRELI - 39611288/0001-76 - debysab@hotmail.com | V99: CECAM | W99: AV. RESINDO PAVAN - N 3177, ESTALEIRO
B100: OTÁVIO AUGUSTUS TONIOLO | C100: MÃE: 47 99638 1225 PAI: 41 99877 0608 | D100: - | I100: 1 | J100: OK | K100: 13059925984 | M100: 45643 | N100: OK | O100: OK | R100: AB+ | S100: 42058 | T100: 4 | U100: CRISTIANE WILLERS - 005.087.350-41 - CRISTIANEW1904@GMAIL.COM | V100: JOÃO VIRGILIO | W100: R. OLAVIO LOURENÇO - N 44, CEDRO
...

Sheet ANUAL
A1: MÊS | B1: ENTRADA MENSAL | C1: SAÍDA MENSAL | D1: FATURAMENTO MENSAL
A2: JANEIRO | B2: =SUM(JAN!B2:B65) -> 9180 | C2: =SUM(JAN!C2:C65) -> 0 | D2: =B2-C2 -> 9180
A3: FEVEREIRO | B3: =SUM(FEV!B3:B62) -> 3007 | C3: =SUM(FEV!C3:C62) -> 0 | D3: =B3-C3 -> 3007
A4: MARÇO | B4: =SUM(MAR!B3:B63) -> 4080 | C4: =SUM(MAR!C3:C63) -> 0 | D4: =B4-C4 -> 4080
A5: ABRIL | B5: =SUM(ABR!B3:B64) -> 4206.5 | C5: =SUM(ABR!C3:C64) -> 0 | D5: =B5-C5 -> 4206.5
A6: MAIO | B6: =SUM(MAI!B3:B65) -> 9702.5 | C6: =SUM(MAI!C3:C65) -> 0 | D6: =B6-C6 -> 9702.5
A7: JUNHO | B7: =SUM(JUN!B3:B66) -> 8412 | C7: =SUM(JUN!C3:C66) -> 0 | D7: =B7-C7 -> 8412
A8: JULHO | B8: =SUM(JUL!B3:B67) -> 15122 | C8: =SUM(JUL!C3:C67) -> 0 | D8: =B8-C8 -> 15122
A9: AGOSTO | B9: =SUM(AGO!B4:B70) -> 18186 | C9: =SUM(AGO!C4:C70) -> 0 | D9: =B9-C9 -> 18186
A10: SETEMBRO | B10: =SUM(SET!B3:B72) -> 20017 | C10: =SUM(SET!C3:C72) -> 0 | D10: =B10-C10 -> 20017
A11: OUTUBRO | D11: =B11-C11 -> 0
A12: NOVEMBRO | D12: =B12-C12 -> 0
A13: DEZEMBRO | D13: =B13-C13 -> 0
A14: ANO | B14: =SUM(B2:B13) -> 91913 | C14: =SUM(C1:C13) -> 0 | D14: =SUM(D2:D13) -> 91913

Sheet MAI
E1: CAIXA ESCOLINHA MAIO 2026
A2: DATA: | B2: ENTRADA: | C2: SAÍDA: | D2: TIPO: | E2: REFERÊNCIA: | F2: Coluna 1 | G2: TOTAL DE ENTRADA | H2: TOTAL DE SAÍDA | I2: FATURAMENTO MENSAL
A3: 46146 | B3: 230 | D3: CRÉDITO 4X | E3: UNIFORME ADRIAN DE BAIRROS | F3: UNIFORME | G3: =SUM(B2:B41) -> 9702.5 | H3: =SUM(C2:C41) -> 0 | I3: =G3-H3 -> 9702.5
A4: 46147 | B4: 40 | D4: PIX | E4: MEIÃO 28-32 AZUL | F4: UNIFORME
A5: 46147 | B5: 300 | D5: PIX | E5: LUCAS MENEGUSSO PEREIRA DA ROCHA - MARÇO MENSALIDADE | F5: MENSALIDADE
A6: 46149 | B6: 350 | D6: PIX | E6: PIETRO RIFFEL COUTO - MENSALIDADE MAIO | F6: MENSALIDADE
A7: 46149 | B7: 65 | D7: CRÉDITO A VISTA | E7: CALÇÃO | F7: UNIFORME
A8: 46150 | B8: 300 | D8: PIX | E8: YAN CHISTOPHER MACHADO PEREIRA - MENSALIDADE ABRIL | F8: MENSALIDADE
A9: 46153 | B9: 332.5 | D9: DÉBITO | E9: DAVI FONSECA BEUTING - MENSALIDADE MAIO | F9: MENSALIDADE
A10: 46154 | B10: 230 | D10: DINHEIRO | E10: JOHN ADAMS NERVARD - MENSALIDADE MAIO | F10: MENSALIDADE
A11: 46160 | B11: 280 | D11: CRÉDITO | E11: MIGUEL CORREIA DE FREITAS - MENSALIDADE ABRIL | F11: MENSALIDADE
A12: 46160 | B12: 180 | D12: CRÉDITO | F12: MENSALIDADE
A13: 46161 | B13: 330 | D13: PIX | E13: GUSTAVO KENJI DA SILVEIRA - MENSALIDADE MAIO | F13: MENSALIDADE
A14: 46161 | B14: 250 | D14: PIX | E14: DAVI PEREIRA - MENSALIDADE MAIO | F14: MENSALIDADE
A15: 46163 | B15: 250 | D15: PIX | E15: BENTO GHENO GONÇALVES - MENSALIDADE ABRIL | F15: MENSALIDADE
A16: 46163 | B16: 140 | D16: PIX | E16: CAMISETA - 684 | F16: UNIFORME
A17: 46163 | B17: 3780 | D17: CREDITO 12X | E17: DAVI MARQUES DA SILVA E VICENTE MARQUES DA SILVA - ANUAL MENSALIDADE | F17: MENSALIDADE
A18: 46163 | B18: 990 | D18: CRÉDITO 3X | E18: GABRIEL OSÓRIO - MAIO, JUNHO E JULHO MENSALIDADE | F18: MENSALIDADE
A19: 46163 | B19: 300 | D19: PIX | E19: DAVI LUCAS ZANELLA TONESER - MENSALIDADE MAIO | F19: MENSALIDADE
A20: 46164 | B20: 65 | D20: PIX | E20: JOSEP - CALÇÃO GG
A21: 46170 | B21: 240 | D21: PIX | E21: UNIFORME MIGUEL PACHECO - CALÇÃO G E CAMISA 692 | F21: UNIFORME
A22: 46170 | B22: 250 | D22: PIX | E22: GABRIEL COELHO - MENSALIDADE | F22: MENSALIDADE
A23: 46171 | B23: 250 | D23: DINHEIRO | E23: JOÃO GERGENSLEY LAGUERRE - MENSALIDADE ABRIL | F23: MENSALIDADE
A24: 46154 | B24: 250 | D24: PIX | E24: DAVI LUCIANO DOMINICIANO - MENSALIDADE
A25: 46165 | B25: 300 | D25: PIX | E25: MIGUEL PACHECO DO NASCIMENTO - MENSALIDADE MAIO | F25: MENSALIDADE

Sheet JUN
E1: CAIXA ESCOLINHA JUNHO 2026
A2: DATA: | B2: ENTRADA: | C2: SAÍDA: | D2: TIPO: | E2: REFERÊNCIA: | F2: TIPO
A3: 46175 | B3: 350 | D3: PIX | E3: GUILHERME PEREIRA DOS SANTOS - MENSALIDADE MAIO | F3: MENSALIDADE | H3: TOTAL DE ENTRADA | I3: TOTAL DE SAÍDA | J3: FATURAMENTO MENSAL
A4: 46178 | B4: 220 | D4: DINHEIRO | E4: PEDRO HENRIQUE LIMA DA SILVA - MENSALIDADE JUNHO RETORNOU DO ATESTADO | F4: MENSALIDADE | H4: =SUM(B3:B42) -> 8412 | I4: =SUM(C3:C42) -> 0 | J4: =H4-I4 -> 8412
A5: 46182 | B5: 180 | D5: PIX | E5: DAVI LUCIANO DOMINICIANO - MENSALIDADE JUNHO | F5: MENSALIDADE
A6: 46184 | B6: 330 | D6: PIX | E6: GUSTAVO KENJI DA SILVEIRA - MENSALIDADE JUNHO | F6: MENSALIDADE
A7: 46184 | B7: 200 | D7: PIX | E7: HENRI CARPENEDO DOS SANTOS - MENSALIDADE ABRIL | F7: MENSALIDADE
A8: 46184 | B8: 200 | D8: PIX | E8: HENRI CARPENEDO DOS SANTOS - MENSALIDADE MAIO | F8: MENSALIDADE
A9: 46188 | B9: 500 | D9: PIX | E9: PEDRO HENRIQUE BELICA GASPAR - MENSALIDADE MAIO E JUNHO | F9: MENSALIDADE
A10: 46192 | B10: 280 | D10: PIX | E10: EMANUEL SIMAS MACHADO - MENSALIDADE ABRIL | F10: MENSALIDADE
A11: 46195 | B11: 280 | D11: CRÉDITO | E11: MIGUEL CORREIA DE FREITAS - MENSALIDADE DE MAIO | F11: MENSALIDADE
A12: 46188 | B12: 332 | D12: DINHEIRO | E12: SARA E DAVI FONSECA - MENSALIDADE DE JUNHO | F12: MENSALIDADE
A13: 46195 | B13: 350 | D13: PIX | E13: Pietro Riffel Couto - MENSALIDADE JUNHO | F13: MENSALIDADE
A14: 46195 | B14: 300 | D14: PIX | E14: Lucas Menegusso Pereira Da Rocha - MENSALIDADE ABRIL | F14: MENSALIDADE
A15: 46195 | B15: 250 | D15: PIX | E15: Davi Lucas Zanella Tonezer - MENSALIDADE JUNHO | F15: MENSALIDADE
A16: 46195 | B16: 250 | D16: PIX | E16: MICHAEL NUNES BARBOSA - MENSALIDADE ABRIL | F16: MENSALIDADE
... A32: 46199 | B32: 350 | D32: PIX | E32: ARTHUR HINCKEL DALLAGNO - MENSALIDADE JUNHO | F32: MENSALIDADE
A33: 46199 | D33: PIX | E33: CARLOS PYETRO MATOS DE SOUZA - MENSALIDADE MAIO | F33: MENSALIDADE
A34: 46199 | B34: 250 | D34: PIX | E34: LORENZO PERONIO ZAMBELE - MENSALIDADE MAIO | F34: MENSALIDADE
A35: 46199 | B35: 250 | D35: PIX | E35: MARTIN PERONIO ZAMBELE - MENSALIDADE MAIO | F35: MENSALIDADE
A36: 46199 | B36: 250 | D36: PIX | E36: LORENZO PERONIO ZAMBELE - MENSALIDADE JUNHO | F36: MENSALIDADE
A37: 46199 | B37: 250 | D37: PIX | E37: MARTIN PERONIO ZAMBELE - MENSALIDADE JUNHO | F37: MENSALIDADE

Sheet JUL
E1: CAIXA ESCOLINHA JULHO 2026
A2: DATA | B2: ENTRADA | C2: SAÍDA | D2: TIPO | E2: REFERÊNCIA | F2: TIPO
A3: 46204 | B3: 300 | D3: PIX | E3: DAVI DE SOUZA SEBEN - MENSALIDADE MAIO | F3: MENSALIDADE | G3: TOTAL DE ENTRADA | H3: TOTAL DE SAÍDA | I3: FATURAMENTO MENSAL
A4: 46204 | B4: 300 | D4: PIX | E4: DAVI DE SOUZA SEBEN - MENSALIDADE JUNHO | F4: MENSALIDADE | G4: =SUM(B3:B50) -> 12587 | H4: =SUM(C3:C42) -> 0 | I4: =G4-H4 -> 12587
A5: 46204 | B5: 300 | D5: PIX | E5: MICHAEL NUNES BARBOSA - MENSALIDADE MAIO | F5: MENSALIDADE
A6: 46204 | B6: 300 | D6: PIX | E6: MICHAEL NUNES BARBOSA - MENSALIDADE JUNHO | F6: MENSALIDADE
A7: 46147 | B7: 250 | D7: PIX | E7: EDUARDO PEDRO BOM CORDEIRO - MENSALIDADE MAIO | F7: MENSALIDADE
A8: 46204 | B8: 250 | D8: PIX | E8: GABRIEL QUEIROZ WITHOFT - MENSALIDADE JUNHO | F8: MENSALIDADE
A9: 46204 | B9: 350 | D9: PIX | E9: GUILHERME PEREIRA DOS SANTOS - MENSALIDADE JUNHO | F9: MENSALIDADE
A10: 46205 | B10: 200 | D10: PIX | E10: HENRI CARPENEDO DOS SANTOS - MENSALIDADE JUNHO | F10: MENSALIDADE
A11: 46206 | B11: 250 | D11: PIX | E11: EDUARDO PEDRO BOM CORDEIRO - MENSALIDADE ABRIL | F11: MENSALIDADE
A12: 46209 | B12: 180 | D12: PIX | E12: ANTÔNIO SALVADOR - MENSALIDADE JUNHO | F12: MENSALIDADE
A13: 46209 | B13: 250 | D13: PIX | E13: PEDRO HENRIQUE BELICA GASPAR | F13: MENSALIDADE
A14: 46211 | B14: 320 | D14: DINHEIRO | E14: ISABELLA MARIA PINHEIRO - MENSALIDADE JULHO E AGOSTO | F14: MENSALIDADE
A15: 46212 | B15: 230 | D15: DINHEIRO | E15: JOHN ADAMS NERVARD - MENSALIDADE JULHO | F15: MENSALIDADE
A16: 46212 | B16: 25 | D16: PIX | E16: LUCAS GABRIEL DA SILVA CORDEIRO - GARRAFINHA | F16: OUTROS
... A27: 46217 | B27: 350 | D27: PIX | E27: PEDRO DAVI LOCH - MENSALIDADE | F27: MENSALIDADE
A28: 46217 | B28: 230 | D28: PIX | E28: PEDRO DAVI LOCH - UNIFORME | F28: UNIFORME | G28: UNIFORMES: | H28: =SUM(B28,B40,B44) -> 860
A29: 46217 | B29: 180 | D29: BOLETO | E29: LEONARDO DAVI PEREIRA ROGAL - MENSALIDADE JULHO | F29: MENSALIDADE | G29: MENSALIDADES: | H29: =SUM(B3:B15,B17:B20,B23:B27,B29:B33,B35:B39,B42:B43,B45:B48) -> 10682
A30: 46218 | B30: 200 | D30: PIX | E30: HENRI CARPENEDO DOS SANTOS - MENSALIDADE JULHO | F30: MENSALIDADE | G30: OUTROS: | H30: =SUM(B22,B21,B16,B34,B41) -> 545
A31: 46218 | B31: 300 | D31: PIX | E31: YAN CHISTOPHER MACHADO PEREIRA - MENSALIDADE JULHO | F31: MENSALIDADE
A32: 46218 | B32: 250 | D32: PIX | E32: BENTO GHENO GONÇALVES - MENSALIDADE JULHO | F32: MENSALIDADE | G32: TOTAL | H32: =SUM(H28:H30) -> 12087
A33: 46218 | B33: 270 | D33: PIX | E33: ISACK CABRAL FINOTTI - Mensalidade Julho | F33: MENSALIDADE
A34: 46219 | B34: 25 | D34: CREDITO | E34: BENTO GHENO GONÇALVES - GARRAFINHA | F34: OUTROS
A35: 46219 | B35: 250 | D35: PIX | E35: GABRIEL QUEIRÓZ WITHOFT - MENSALIDADE MAIO | F35: MENSALIDADE
A36: 46189 | B36: 300 | D36: PIX | E36: LUCAS MENEGUSSO PEREIRA DA ROCHA - MENSALIDADE JUNHO | F36: MENSALIDADE
A37: 46189 | B37: 300 | D37: PIX | E37: LUCAS MENEGUSSO PEREIRA DA ROCHA - MENSALIDADE JULHO | F37: MENSALIDADE
A38: 46219 | B38: 350 | D38: PIX | E38: JOAO PEDRO MENEZES KNECHTEL - MENSALIDADE JUNHO | F38: MENSALIDADE
A39: 46219 | B39: 350 | D39: PIX | E39: JOAO PEDRO MENEZES KNECHTEL - MENSALIDADE JULHO | F39: MENSALIDADE
A40: 46220 | B40: 230 | D40: PIX | E40: Anthony Carvalho - Uniforme | F40: UNIFORME
A41: 46220 | B41: 25 | D41: PIX | E41: Anthony Carvalho - Garrafinha | F41: OUTROS
A42: 46220 | B42: 225 | D42: DINHEIRO | E42: CARLOS PYETRO MATOS DE SOUZA - MENSALIDADE JUNHO | F42: MENSALIDADE
A43: 46220 | B43: 350 | D43: PIX | E43: GULHERME HINCKEL DALLAGNO - MENSALIDADE MAIO | F43: MENSALIDADE
A44: 46220 | B44: 400 | D44: CREDITO 3X | E44: PIETRO E MIGUEL SCHIAVON - UNIFORMES | F44: UNIFORME
... A58: 46234 | B58: 230 | D58: PIX | E58: UNIFORME RYAN CARLOS | F58: UNIFORME

Sheet AGO
A2: DATA: | B2: ENTRADA: | C2: SAÍDA: | D2: TIPO: | E2: REFERÊNCIA: | F2: TIPO
A3: 46237 | B3: 170 | D3: DINHEIRO | E3: LUCAS EVANGELISTA DE SOUZA - MENSALIDADE DE JULHO | F3: MENSALIDADE | H3: TOTAL DE ENTRADA | I3: TOTAL DE SAÍDA | J3: FATURAMENTO MENSAL
A4: 46237 | B4: 170 | D4: DINHEIRO | E4: LUCAS EVANGELISTA DE SOUZA - MENSALIDADE DE AGOSTO | F4: MENSALIDADE | H4: =SUM(B3:B51) -> 17401 | I4: =SUM(C3:C43) -> 0 | J4: =H4-I4 -> 17401
A5: 46237 | B5: 225 | D5: DÉBITO | E5: RAJI GHAITH - MENSALIDADE AGOSTO | F5: MENSALIDADE
A6: 46237 | B6: 275 | D6: DÉBITO | E6: RAYAN GHAITH - MENSALIDADE AGOSTO | F6: MENSALIDADE
A7: 46237 | B7: 350 | D7: DÉBITO | E7: RAYAN E RAJI GHAITH - UNIFORMES | F7: UNIFORME
A8: 46238 | B8: 270 | D8: DINHEIRO | E8: HENRIQUE LOTTI - MENSALIDADE | F8: MENSALIDADE
A9: 46238 | B9: 230 | D9: PIX | E9: Lucas Fernando Delagnello - MENSALIDADE | F9: MENSALIDADE
A10: 46240 | B10: 140 | D10: CREDITO | E10: ISACK CABRAL FINOTTI - UNIFORME | F10: UNIFORME
A11: 46240 | B11: 900 | D11: CRÉDITO 3X | E11: GABRIEL OSÓRIO GUEDES - MENSALIDADE JULHO - OUTUBRO | F11: MENSALIDADE
A12: 46240 | B12: 195 | D12: CRÉDITO | E12: MIGUEL STOLFI - UNIFORME - CAMISETA E CALÇÃO | F12: UNIFORME
A13: 46240 | B13: 280 | D13: PIX | E13: EMANUEL SIMAS MACHADO - JUNHO | F13: MENSALIDADE
A14: 46241 | B14: 140 | D14: CREDITO | E14: BRYAN BELICA GASPAR - UNIFORME | F14: UNIFORME
A15: 46241 | B15: 350 | D15: PIX | E15: HIROYUKI MOTA TUKAMOTO - MENSALIDADE AGOSTO | F15: MENSALIDADE
A16: 46244 | B16: 180 | D16: PIX | E16: ANTÔNIO SALVADOR - MENSALIDADE AGOSTO | F16: MENSALIDADE
... A51: 46290 | B51: 225 | D51: DINHEIRO | E51: JOSÉ JOAQUIN YUNIS - MENSALIDADE | F51: MENSALIDADE
A52: 46290 | D52: CREDITO | E52: ATHUR SIMAS - UNIFORME | F52: UNIFORME
A53: 46290 | D53: DINHEIRO | E53: ARTHUR SIMAS - MENSALIDADE | F53: MENSALIDADE
A54: 46261 | B54: 230 | D54: PIX | E54: UNIFORME - ENZO | F54: UNIFORME
A55: 46262 | B55: 225 | D55: DINHEIRO | E55: CARLOS PYETRO MATOS DE SOUZA - MENSALIDADE AGOSTO | F55: MENSALIDADE
A56: 46246 | B56: 300 | D56: PIX | E56: PEDRO KRENKHE - MENSALIDADE | F56: MENSALIDADE
A57: 46254 | B57: 200 | D57: PIX | E57: HENRI CARPENEDO | F57: MENSALIDADE

Sheet SET
E1: CAIXA ESCOLINHA SETEMBRO 2026
A2: DATA | B2: ENTRADA | C2: SAÍDA | D2: TIPO | E2: REFERÊNCIA | F2: TIPO
A3: 46266 | B3: 250 | D3: CREDITO | E3: DAVI GOMES SILVEIRA - MENSALIDADE | F3: MENSALIDADE | G3: TOTAL DE ENTRADA | H3: TOTAL DE SAÍDA | I3: FATURAMENTO MENSAL
A4: 46266 | B4: 230 | D4: CREDITO | E4: UNIFORME JOSÉ JOAQUIM | F4: UNIFORME | G4: =SUM(B3:B50) -> 17859 | H4: =SUM(C3:C42) -> 0 | I4: =G4-H4 -> 17859
A5: 46266 | B5: 185 | D5: PIX | E5: GUSTAVO KENJI - CAMISA JOGO E CAMISA UNIFORME | F5: UNIFORME
A6: 46268 | B6: 250 | D6: PIX | E6: RICARDO TERESKOVAC - MENSALIDADE | F6: MENSALIDADE
A7: 46268 | B7: 250 | D7: PIX | E7: EDUARDO PEDRO BOM CORDEIRO - MENSALIDADE | F7: MENSALIDADE
A8: 46268 | B8: 700 | D8: PIX | E8: GULHERME E ARTHUR HINCKEL DALLAGNO - JULHO | F8: MENSALIDADE
A9: 46268 | B9: 225 | D9: DINHEIRO | E9: LORENZO DOS SANTOS DE OLIVEIRA- MENSALIDADE | F9: MENSALIDADE
A10: 46268 | B10: 200 | D10: DINHEIRO | E10: LORENZO DOS SANTOS DE OLIVEIRA - UNIFORME | F10: UNIFORME
A11: 46269 | B11: 200 | D11: DINHEIRO | E11: GIORGIO - UNIFORME | F11: UNIFORME
A12: 46269 | B12: 300 | D12: DÉBITO | E12: PEDRO KRENK - MENSALIDADE | F12: MENSALIDADE
A13: 46269 | B13: 270 | D13: DINHEIRO | E13: ANTHONY GABRIEL DA SILVA - MENSALIDADE | F13: MENSALIDADE
A14: 46273 | B14: 315 | D14: DINHEIRO | E14: ARTHUR VALENDORFF DE CARVALHO - MNESALIDADE | F14: MENSALIDADE
A15: 46273 | B15: 250 | D15: PIX | E15: Antônio Jacotto Neto - MENSALIDADE | F15: MENSALIDADE
A16: 46273 | B16: 250 | D16: PIX | E16: CICERO DE CASTRO DAPIEVE - MENSALIDADE | F16: MENSALIDADE
... A27: 46279 | B27: 250 | D27: PIX | E27: MIGUEL YUTA KANAI - MENSALIDADE | F27: MENSALIDADE
A28: 46279 | B28: 475 | D28: PIX | E28: AYLA E DAVI FIDENCIO - DIVIDA MENS. JULHO | F28: MENSALIDADE | G28: UNIFORMES: | H28: =SUM(B28,B40,B44) -> 860
A29: 46279 | B29: 350 | D29: CRÉDITO | E29: MIGUEL STOLFI - MENSALIDADE | F29: MENSALIDADE | G29: MENSALIDADES: | H29: =SUM(B3:B15,B17:B20,B23:B27,B29:B33,B35:B39,B42:B43,B45:B48) -> 14301
A30: 46279 | B30: 332 | D30: DÉBITO | E30: DAVI FONSECA BEUTING - MENSALIDADE | F30: MENSALIDADE | G30: OUTROS: | H30: =SUM(B22,B21,B16,B34,B41) -> 943
A31: 46280 | B31: 230 | D31: DINHEIRO | E31: JOHN ADAMS - MENSALIDADE | F31: MENSALIDADE
A32: 46280 | B32: 400 | D32: DINHEIRO | E32: DAVI SEBEN - MENSALIDADE JULHO E AGOSTO | F32: MENSALIDADE | G32: TOTAL | H32: =SUM(H28:H30) -> 16104
A33: 46280 | B33: 475 | D33: PIX | E33: AYLA E DAVI FIDENCIO - MENS. SETEMBRO | F33: MENSALIDADE
A34: 46280 | B34: 45 | D34: PIX | E34: ARTHUR HINCKEL - MEIÃO | F34: UNIFORME
A35: 46273 | B35: 250 | D35: PIX | E35: CICERO DE CASTRO DAPIEVE - MENSALIDADE | F35: MENSALIDADE
A36: 46273 | B36: 250 | D36: PIX | E36: ANTÔNIO JACOTTO NETO - MENSALIDADE | F36: MENSALIDADE
A37: 46280 | B37: 230 | D37: DINHEIRO | E37: PEDRO HENRIQUE LIMA DA SILVA - MENSALIDADE | F37: MENSALIDADE
A38: 46282 | B38: 65 | D38: CREDITO | E38: THOMAS GERALDO - CALÇÃO UNIFORME | F38: UNIFORME
A39: 46282 | B39: 500 | D39: CREDITO | E39: RAJI E RAYAN GHAITH - MENSALIDADE | F39: MENSALIDADE
A40: 46283 | B40: 180 | D40: PIX | E40: BRAYAN BELICA DALMOLIN - mensalidade | F40: MENSALIDADE
A41: 46283 | B41: 280 | D41: CREDITO | E41: MIGUEL CORREIA DE FREITAS - MENSALIDADE | F41: MENSALIDADE
A42: 46286 | B42: 162 | D42: DINHEIRO | E42: LUCAS EVANGELISTA - MENSALIDADE | F42: MENSALIDADE
A43: 46286 | B43: 180 | D43: Pix | E43: ANTÔNIO SALVADOR SOARES - Mensalidade | F43: MENSALIDADE
A44: 46283 | B44: 205 | D44: CREDITO | E44: MIGUEL YUTA - UNIFORME CALÇÃO E CAMISA | F44: UNIFORME
A45: 46288 | E45: YAN CHISTOPHER MACHADO PEREIRA | F45: MENSALIDADE
A46: 46289 | B46: 500 | D46: CREDITO | E46: MARTIN E LORENZO PERONIO | F46: MENSALIDADE
A47: 46286 | B47: 3402 | D47: CREDITO 12X | E47: JOSÉ MIGUEL DA SILVA - MENS 12 MESES | F47: MENSALIDADE
A48: 46293 | B48: 200 | D48: PIX | E48: HENRI CARPENEDO DOS SANTOS - MENSALIDADE SET | F48: MENSALIDADE
A49: 46290 | B49: 45 | D49: DEBITO | E49: SARA FONSECA - UNIFORME MEIAO | F49: UNIFORME
A50: 46294 | B50: 1710 | D50: CREDITO 6X | E50: DOM MENSALIDADE 6 MESES | F50: MENSALIDADE
A51: 46294 | B51: 250 | D51: PIX | E51: VICTOR WILLIAN NEUCAMP MENSALIDADE | F51: MENSALIDADE
A52: 46294 | B52: 180 | D52: BOLETO | E52: LEONARDO ROGAL - MENSALIDADE | F52: MENSALIDADE
A53: 46295 | B53: 243 | D53: PIX | E53: GUILHERME DERETTI MENSALIDADE | F53: MENSALIDADE
A54: 46295 | B54: 350 | D54: PIX | E54: PEDRO DAVI LOCH MENSALIDADE | F54: MENSALIDADE
A55: 46295 | B55: 250 | D55: PIX | E55: GABRIEL QUEIRÓZ WITHOFT - MENS AGOSTO | F55: MENSALIDADE
A56: 46296 | B56: 250 | D56: PIX | E56: LUCAS MENEGUSSO PEREIRA DA ROCHA - MENSALIDADE | F56: MENSALIDADE
A57: 46296 | B57: 225 | D57: DINHEIRO | E57: CARLOS PYETRO MATOS DE SOUZA - MENSALIDADE | F57: MENSALIDADE
... A59: 46296 | B59: 250 | D59: DINHEIRO | E59: DAVI SEBEN - MENSALIDADE SETEMBRO | F59: MENSALIDADE

Sheet DEZ
E1: CAIXA ESCOLINHA NOVEMBRO- 2025
A2: DATA | B2: ENTRADA | C2: SAÍDA | D2: TIPO | E2: ALUNO | F2: CPF | G2: TOTAL DE ENTRADA | H2: TOTAL DE SAÍDA | I2: FATURAMENTO MENSAL
G5: =SUM(B2:B43) -> 0 | H5: =SUM(C5:C43) -> 0 | I5: =G5-H5 -> 0

Sheet NOV
E1: CAIXA ESCOLINHA NOVEMBRO- 2025
A2: DATA | B2: ENTRADA | C2: SAÍDA | D2: TIPO | E2: ALUNO | F2: CPF | G2: TOTAL DE ENTRADA | H2: TOTAL DE SAÍDA | I2: FATURAMENTO MENSAL
G3: =SUM(B2:B41) -> 0 | H3: =SUM(C3:C41) -> 0 | I3: =G3-H3 -> 0

Sheet ABR
E1: CAIXA ESCOLINHA ABRIL 2026
A2: DATA | B2: ENTRADA | C2: SAÍDA | D2: TIPO | E2: REFERÊNCIA | G2: TOTAL DE ENTRADA | H2: TOTAL DE SAÍDA | I2: FATURAMENTO MENSAL
A3: 46126 | B3: 350 | D3: PIX | E3: JOÃO PEDRO MENEZES KNETCHEL - MENSALIDADE ABRIL | G3: =SUM(B2:B41) -> 4206.5 | H3: =SUM(C2:C41) -> 0 | I3: =G3-H3 -> 4206.5
A4: 46135 | B4: 300 | D4: PIX | E4: DAVI LUCAS ZANELLA TONESER - MENSALIDADE ABRIL
A5: 46135 | B5: 140 | D5: DÉBITO | E5: JOHN ADAMS NERVARD - CAMISETA 673
A6: 46122 | B6: 250 | D6: PIX | E6: PEDRO HENRIQUE BELICA GASPAR - MENSALIDADE ABRIL
A7: 46136 | B7: 250 | D7: PIX | E7: GABRIEL QUEIRÓZ WITHOFT - MENSALIDADE ABRIL
A8: 46139 | B8: 285 | D8: CRÉDITO 2X | E8: MIGUEL CORREIA DE FREITAS - MENSALIDADE MARÇO
A9: 46140 | B9: 140 | D9: DÉBITO | E9: CAMISETA GOLEIRO TAM 10
A10: 46141 | B10: 1334 | D10: CRÉDITO 4X | E10: JOÃO VICTOR MICHELETTI ROHRS - MENSALIDADE 6 MESES
A11: 46128 | B11: 332.5 | D11: DÉBITO | E11: DAVI FONSECA BEUTING - MENSALIDADE ABRIL
A12: 46142 | B12: 475 | D12: CRÉDITO | E12: LORENZO E MARTIN PERONIO ZAMBELI - MENSALIDADE ABRIL
A13: 46119 | B13: 350 | D13: PIX | E13: GUSTAVO KENJI DA SILVEIRA - MENSALIDADE ABRIL

Sheet MAR
E1: CAIXA ESCOLINHA MARÇO 2026
A2: DATA | B2: ENTRADA | C2: SAÍDA | D2: TIPO | E2: REFERÊNCIA | G2: TOTAL DE ENTRADA | H2: TOTAL DE SAÍDA | I2: FATURAMENTO MENSAL
A3: 46090 | B3: 350 | D3: PIX | E3: MENSALIDADE JANEIRO - ARTHUR HINCKEL DALLAGNO | G3: =SUM(B2:B90) -> 4080 | H3: =SUM(C2:C51) -> 0 | I3: =G3-H3 -> 4080
A4: 46090 | B4: 350 | D4: PIX | E4: MENSALIDADE JANEIRO - GUSTAVO KENJI DA SILVEIRA
A5: 46084 | B5: 450 | D5: PIX | E5: Lucas Menegusso Pereira Da Rocha /prart Rochel/pai
A6: 46084 | B6: 180 | D6: PIX | E6: DOUGLAS BROCHIER RODRIGUES - PARTICULAR
A7: 46091 | B7: 1425,00/ 6x | C7: 420,00 uniforme | D7: cartão | E7: BENJAMIN PIOPELLI CXOSTA | F7: 6 MESES 10/03
A8: 46091 | B8: 250 | D8: pix | E8: Davi Luciano Domiciano - Particular
A9: 46091 | B9: 250 | D9: pix | E9: Davi Fidencio / Particular
A10: 46097 | B10: 250 | D10: pix | E10: Henri Carpenedo Dos Santos Particular
A11: 46105 | B11: 500 | D11: cartao | E11: Lorenzo E Martim / particular
A12: 46108 | B12: 350 | D12: pix | E12: EDUARDO PEDRO BOM CORDEIRO/ PART FERNANDA /MÃE
A13: 46093 | B13: 350 | D13: pix | E13: João Pedro Menezes Knechtel - Particular
A14: 46098 | B14: 250 | D14: pix | E14: GABRIEL TALES MENOTTI /PART
A15: 46118 | B15: 250 | D15: PIX | E15: Davi Luciano Domiciano - Particular
A16: 46125 | B16: 300

Sheet FEV
E1: CAIXA ESCOLINHA FEVEREIRO 2026
A2: DATA | B2: ENTRADA | C2: SAÍDA | D2: TIPO | E2: REFERÊNCIA | F2: TOTAL DE ENTRADA | G2: TOTAL DE SAÍDA | H2: FATURAMENTO MENSAL
A3: 46056 | B3: 312 | D3: DINHEIRO | E3: MENSALIDADE E MATRÍCULA - GUSTAVO DA ROCHA HIRT | F3: =SUM(B2:B41) -> 3007 | G3: =SUM(C2:C41) -> 0 | H3: =F3-G3 -> 3007
A4: 46056 | B4: 240 | D4: PIX | E4: UNIFORME COMPLETO
A5: 46055 | B5: 330 | D5: PIX | E5: MENSALIDADE FEVEREIRO - GUSTAVO KENJI DA SILVEIRA
A6: 46058 | B6: 250 | D6: DINHEIRO | E6: MENSALIDADE JANEIRO - JOÃO GERGENSLEY LAGUERRE
A7: 46058 | B7: 465 | D7: PIX | E7: MENSALIDADE E UNIFORME - BENTO GHENO GONÇALVES
A8: 46063 | B8: 250 | D8: PIX | E8: MENSALIDADE ANTONIO BLANCO GARCIA ROSA
A9: 46063 | B9: 230 | D9: DINHEIRO | E9: MENSALIDADE - JOHN ADAMS NERVARD
A10: 46062 | B10: 350 | D10: DINHEIRO | E10: MENSALIDADE JANEIRO - AYO MIGUEL CAMPOS DOMINGUES
A11: 46062 | B11: 350 | D11: DEBITO | E11: MENSALIDADE FEVEREIRO DAVI FONSECA
A12: 46076 | B12: 230 | D12: PIX | E12: MENSALIDADE - LUCAS DE SOUZA BARRETO

Sheet JAN
E1: CAIXA ESCOLINHA JANEIRO 2026
A2: DATA | B2: ENTRADA | C2: SAÍDA | D2: TIPO | E2: REFERÊNCIA | F2: TOTAL DE ENTRADA | G2: TOTAL DE SAÍDA | H2: FATURAMENTO MENSAL
A3: 46034 | B3: 280 | D3: PIX | E3: MENSALIDADE EMANUEL SIMAS MACHADO - NOVEMBRO 2025 | F3: =SUM(B2:B45) -> 9180 | G3: =SUM(C2:C45) -> 0 | H3: =F3-G3 -> 9180
A4: 46037 | B4: 250 | D4: DÉBITO | E4: MENSALIDADE DAVI LUCIANO
A5: 46042 | B5: 250 | D5: PIX | E5: MENSALIDADE CARLOS PYETRO - DEZEMBRO 2025
A6: 46042 | B6: 230 | D6: DINHEIRO | E6: MENSALIDADE JOHN ADAMS NERVARD - JANEIRO 2026
A7: 46042 | B7: 250 | D7: PIX | E7: MENSALIDADE PEDRO KREHNKE DE OLIVEIRA - JANEIRO
A8: 46044 | B8: 530 | D8: PIX | E8: CONJUNTO UNIFORME E MENSALIDADE - AUGUSTO GERVASONI
A9: 46045 | B9: 140 | D9: PIX | E9: CAMISETA UNIFORME - ARTHUR HINCKELL DALLAGNO
A10: 46045 | B10: 450 | D10: PIX | E10: LUCAS MENEGUSSO - PAGOU AS MENSALIDADES ATRASADAS (FALTA 450)
A11: 46045 | B11: 280 | D11: DINHEIRO | E11: MENSALIDADE MIGUEL CORREIA DE FREITAS - JANEIRO
A12: 46045 | B12: 3440 | D12: CRÉDITO 10X | E12: MENSALIDADE BERNARDO ROCHA E CAMISETA UNIFORME
A13: 46048 | B13: 280 | D13: PIX | E13: MENSALIDADE EMANUEL SIMAS MACHADO - DEZEMBRO 2025
A14: 46321 | B14: 285 | D14: DINHEIRO | E14: MENSALIDADE MIGUEL PACHECO DO NASCIMENTO - JANEIRO
A15: 46321 | B15: 230 | D15: CRÉDITO | E15: UNIFORME MIGUEL PACHECO DO NASCIMENTO - NÃO PEGOU, DEIXAR RESERVADO CALÇÃO M BLUSA G
A16: 46322 | B16: =855+180 -> 1035 | D16: CRÉDITO | E16: VITOR HICHMEH MENSALIDADE 6 MESES
A17: 46322 | B17: 140 | D17: CRÉDITO | E17: CAMISETA UNIFORME - VITOR HICHMEH
A18: 46049 | B18: 350 | D18: DÉBITO | E18: MENSALIDADE - SARA FONSECA BEUTING
A19: 46049 | B19: 180 | D19: PIX | E19: MENSALIDADE JANEIRO - DOUGLAS BROCHIER RODRIGUES
A20: 46051 | B20: 350 | D20: PIX | E20: MENSALIDADE JANEIRO - GUILHERME PEREIRA DOS SANTOS
A21: 46052 | B21: 230 | D21: CRÉDIO 3X | E21: UNIFORME COMPLETO - MIGUEL CORREIA DE FREITAS
